Workbook
Name BoxPlot: "BoxPlot"
Name Bubble: "Bubble"
Name Candlestick: "Candlestick"
Name Chart: "Chart"
Name ChartImage: "ChartImage"
Name ColumnRange: "ColumnRange"
Name Dumbbell: "Dumbbell"
Name Heatmap: "Heatmap"
Name Histogram: "Histogram"
Name Map: "Map"
Name OHLC: "OHLC"
Name PieChart: "PieChart"
Name Scatter: "Scatter"
Name Series: "Series"
Name Stripe: "Stripe"
Name Table: "Table"
Name TreeMap: "TreeMap"
Name Waterfall: "Waterfall"

Sheet Contents
B2: Source: Mbaye, S., Moreno-Badia, M., and K. Chae. 2018. “Global Debt Database: Methodology and Sources,” IMF Working Paper 18/111, International Monetary Fund, Washington, DC.
B3: Last Update: December 16, 2019.
B5: Global Debt Database
B6: The Global Debt Database (GDD) is the result of a multiyear investigative process that started with the October 2016 Fiscal Monitor. The dataset comprises total gross debt of the (private and public) nonfinancial sector for an unbalanced panel of 190 advanced economies, emerging market economies and low-income countries, dating back to 1950. For more details on the methodology and definitions, please see the Mbaye, Moreno Badia and Chae (2018). We rely on the feedback from users to address any problems they may encounter with the data. Notification of any omissions or supplementary sources is welcome and would be fully acknowledged. Suggestions can be sent to IMF-GDD@imf.org.
B8: Sources
B9: Abbreviation | C9: Full Name | D9: Reference
B10: BIS | C10: Bank of International Settlements | D10: Dembiermont, C., Drehmann M., and Muksakunratana S. 2013. “How Much Does the Private Sector Really Borrow? A New Database for Total Credit to the Private Non-Financial Sector.” BIS Quarterly Review (2013), pp. 65-81.
B11: CEIC | C11: CEIC | D11: https://www.ceicdata.com/en
B12: CLYPS | C12: Cowan, Levy-Yeyati, Panizza and Sturzenegger (2006) | D12: Cowan K., Levy-Yeyati E., Panizza U. and Sturzenegger F. 2006. Sovereign debt in the Americas: new data and stylized facts, RES Working Paper No. 577, Inter-American Development Bank, Research Department, Washington, DC, United States.
B13: Dealogic | C13: Dealogic | D13: http://www.dealogic.com/
B14: Eurostat | C14: Eurostat | D14: Eurostat, http://ec.europa.eu/eurostat/web/main/home, © European Union, 1995 - today
B15: HPDD | C15: Historical Public Debt Database | D15: Abbas, S. Ali, Nazim Belhocine, Asmaa El Ganainy and Mark Horton. 2011. “A Historical Public Debt Database,” IMF Economic Review, vol. 59, iss. 4, pp. 717–42.
B16: IADB | C16: Inter-American Development Bank | D16: Standardized Public Debt Statistics Database, https://mydata.iadb.org/Finance/Standardized-Public-Debt-Database/8c5g-k9ut/data
B17: IFS | C17: International Financial Statistics | D17: International Monetary Fund, International Financial Statistics, Washington DC.
B18: IFS+IDS | C18: Sum of domestic bank lending to the government from the IFS (12a, 22a, 42a) and external debt stocks (public and publicly guaranteed) from World Bank's International Debt Statistics (IDS) | D18: International Monetary Fund, International Financial Statistics, Washington DC. International Debt Statistics, The World Bank.
B19: IMF Staff | C19: International Monetary Fund Staff Estimates | D19: -
B20: JP | C20: Jaimovich and Panizza (2010) | D20: Jaimovich D. and U. Panizza. 2010. "Public debt around the world: a new data set of central government debt," Applied Economics Letters, Taylor and Francis Journals, vol. 17(1), pp. 19-24.
... B34: WEO 2002 | C34: World Economic Outlook (WEO 2002) | D34: International Monetary Fund, September 2002 Vintage, World Economic Outlook, Washington DC.

Sheet Data
C1: =VLOOKUP($C$2,countrylist!$A$1:$B$191,2,0) -> 534
B2: Please Select a Country | C2: India
B4: Sources
B5: Total private debt | F5: Households debt | H5: Non-financial corporations debt | J5: Public sector debt | K5: Nonfinancial public sector debt | L5: General government debt | M5: Central government debt | N5: Nominal gross domestic product
B6: All instruments | C6: Domestic loans | D6: Cross-border loans | E6: Securities | F6: All instruments | G6: Loans and securities | H6: All instruments | I6: Loans and securities
B7: =VLOOKUP($C$1,rawdata!$B$3:$AC$14541,MATCH("tot_all_source", rawdata!$B$3:$AC$3,0),0) | C7: =VLOOKUP($C$1,rawdata!$B$3:$AC$14541,MATCH("dl_source", rawdata!$B$3:$AC$3,0),0) -> BIS (1951-2024) | D7: =VLOOKUP($C$1,rawdata!$B$3:$AC$14541,MATCH("cb_source", rawdata!$B$3:$AC$3,0),0) -> BIS (1951-2024) | E7: =VLOOKUP($C$1,rawdata!$B$3:$AC$14541,MATCH("sec_source", rawdata!$B$3:$AC$3,0),0) -> BIS (1951-2024) | F7: =VLOOKUP($C$1,rawdata!$B$3:$AC$14541,MATCH("hh_all_source", rawdata!$B$3:$AC$3,0),0) | G7: =VLOOKUP($C$1,rawdata!$B$3:$AC$14541,MATCH("hh_ls_source", rawdata!$B$3:$AC$3,0),0) -> National Source (1998-2006); BIS (2007-2024) | H7: =VLOOKUP($C$1,rawdata!$B$3:$AC$14541,MATCH("nfc_all_source", rawdata!$B$3:$AC$3,0),0) | I7: =VLOOKUP($C$1,rawdata!$B$3:$AC$14541,MATCH("nfc_ls_source", rawdata!$B$3:$AC$3,0),0) -> Derived using national source and BIS (1998-2006); BIS (2007-2024) | J7: =VLOOKUP($C$1,rawdata!$B$3:$AC$14541,MATCH("ps_source", rawdata!$B$3:$AC$3,0),0) | K7: =VLOOKUP($C$1,rawdata!$B$3:$AC$14541,MATCH("nfps_source", rawdata!$B$3:$AC$3,0),0) | L7: =VLOOKUP($C$1,rawdata!$B$3:$AC$14541,MATCH("gg_source", rawdata!$B$3:$AC$3,0),0) -> WEO 2025 (1991-2024) | M7: =VLOOKUP($C$1,rawdata!$B$3:$AC$14541,MATCH("cg_source", rawdata!$B$3:$AC$3,0),0) -> R&R (1950-1973); JP (1974-1996); National Source (1998-2024) | N7: =VLOOKUP($C$1,rawdata!$B$3:$AC$14541,MATCH("ngdp_source", rawdata!$B$3:$AC$3,0),0) -> PWT (1950-1961); WEO 2025 (1962-2024)
B8: =IFERROR(IF(VLOOKUP($C$1,footnote!$B$1:$F$215,3,0)=1,"Note: 'National Source' refers to the "&VLOOKUP($C$1,footnote!$B$1:$F$215,4,0)&".","Note: "&VLOOKUP($C$1,footnote!$B$1:$F$215,4,0)&"."), "") -> Note: 'National Source' refers to the Ministry of Finance India, and Reserve Bank of India.
B10: Data
C11: Year | D11: Total private debt, all instruments (percent of GDP) | E11: Total private debt, loans and debt securities (percent of GDP) | F11: Household debt, all instruments (percent of GDP) | G11: Household debt, loans and debt securities (percent of GDP) | H11: Non-financial corporations debt, all instruments (percent of GDP) | I11: Non-financial corporations debt, loans and debt securities (percent of GDP) | J11: Public sector debt (percent of GDP) | K11: Nonfinancial public sector debt (percent of GDP) | L11: General government debt (percent of GDP) | M11: Central government debt (percent of GDP) | N11: Nominal gross domestic product (billions)
C12: 1950 | D12: =IF(ISNUMBER(VLOOKUP($C$1&"-"&$C12,rawdata!$E$3:$AC$14541,MATCH("tot_all_data",rawdata!$E$3:$AC$3,0),0)), VLOOKUP($C$1&"-"&$C12,rawdata!$E$3:$AC$14541,MATCH("tot_all_data",rawdata!$E$3:$AC$3,0),0), "") | E12: =IF(ISNUMBER(VLOOKUP($C$1&"-"&$C12,rawdata!$E$3:$AC$14541,MATCH("tot_ls_data",rawdata!$E$3:$AC$3,0),0)), VLOOKUP($C$1&"-"&$C12,rawdata!$E$3:$AC$14541,MATCH("tot_ls_data",rawdata!$E$3:$AC$3,0),0), "") | F12: =IF(ISNUMBER(VLOOKUP($C$1&"-"&$C12,rawdata!$E$3:$AC$14541,MATCH("hh_all_data",rawdata!$E$3:$AC$3,0),0)), VLOOKUP($C$1&"-"&$C12,rawdata!$E$3:$AC$14541,MATCH("hh_all_data",rawdata!$E$3:$AC$3,0),0), "") | G12: =IF(ISNUMBER(VLOOKUP($C$1&"-"&$C12,rawdata!$E$3:$AC$14541,MATCH("hh_ls_data",rawdata!$E$3:$AC$3,0),0)), VLOOKUP($C$1&"-"&$C12,rawdata!$E$3:$AC$14541,MATCH("hh_ls_data",rawdata!$E$3:$AC$3,0),0), "") | H12: =IF(ISNUMBER(VLOOKUP($C$1&"-"&$C12,rawdata!$E$3:$AC$14541,MATCH("nfc_all_data",rawdata!$E$3:$AC$3,0),0)), VLOOKUP($C$1&"-"&$C12,rawdata!$E$3:$AC$14541,MATCH("nfc_all_data",rawdata!$E$3:$AC$3,0),0), "") | I12: =IF(ISNUMBER(VLOOKUP($C$1&"-"&$C12,rawdata!$E$3:$AC$14541,MATCH("nfc_ls_data",rawdata!$E$3:$AC$3,0),0)), VLOOKUP($C$1&"-"&$C12,rawdata!$E$3:$AC$14541,MATCH("nfc_ls_data",rawdata!$E$3:$AC$3,0),0), "") | J12: =IF(ISNUMBER(VLOOKUP($C$1&"-"&$C12,rawdata!$E$3:$AC$14541,MATCH("ps_data",rawdata!$E$3:$AC$3,0),0)), VLOOKUP($C$1&"-"&$C12,rawdata!$E$3:$AC$14541,MATCH("ps_data",rawdata!$E$3:$AC$3,0),0), "") | K12: =IF(ISNUMBER(VLOOKUP($C$1&"-"&$C12,rawdata!$E$3:$AC$14541,MATCH("nfps_data",rawdata!$E$3:$AC$3,0),0)), VLOOKUP($C$1&"-"&$C12,rawdata!$E$3:$AC$14541,MATCH("nfps_data",rawdata!$E$3:$AC$3,0),0), "") | L12: =IF(ISNUMBER(VLOOKUP($C$1&"-"&$C12,rawdata!$E$3:$AC$14541,MATCH("gg_data",rawdata!$E$3:$AC$3,0),0)), VLOOKUP($C$1&"-"&$C12,rawdata!$E$3:$AC$14541,MATCH("gg_data",rawdata!$E$3:$AC$3,0),0), "") | M12: =IF(ISNUMBER(VLOOKUP($C$1&"-"&$C12,rawdata!$E$3:$AC$14541,MATCH("cg_data",rawdata!$E$3:$AC$3,0),0)), VLOOKUP($C$1&"-"&$C12,rawdata!$E$3:$AC$14541,MATCH("cg_data",rawdata!$E$3:$AC$3,0),0), "") -> 26.127108 | N12: =IF(ISNUMBER(VLOOKUP($C$1&"-"&$C12,rawdata!$E$3:$AC$14541,MATCH("ngdp_data",rawdata!$E$3:$AC$3,0),0)), VLOOKUP($C$1&"-"&$C12,rawdata!$E$3:$AC$14541,MATCH("ngdp_data",rawdata!$E$3:$AC$3,0),0), "") -> 128.03743
C13: 1951 | D13: =IF(ISNUMBER(VLOOKUP($C$1&"-"&$C13,rawdata!$E$3:$AC$14541,MATCH("tot_all_data",rawdata!$E$3:$AC$3,0),0)), VLOOKUP($C$1&"-"&$C13,rawdata!$E$3:$AC$14541,MATCH("tot_all_data",rawdata!$E$3:$AC$3,0),0), "") | E13: =IF(ISNUMBER(VLOOKUP($C$1&"-"&$C13,rawdata!$E$3:$AC$14541,MATCH("tot_ls_data",rawdata!$E$3:$AC$3,0),0)), VLOOKUP($C$1&"-"&$C13,rawdata!$E$3:$AC$14541,MATCH("tot_ls_data",rawdata!$E$3:$AC$3,0),0), "") -> 16.814022 | F13: =IF(ISNUMBER(VLOOKUP($C$1&"-"&$C13,rawdata!$E$3:$AC$14541,MATCH("hh_all_data",rawdata!$E$3:$AC$3,0),0)), VLOOKUP($C$1&"-"&$C13,rawdata!$E$3:$AC$14541,MATCH("hh_all_data",rawdata!$E$3:$AC$3,0),0), "") | G13: =IF(ISNUMBER(VLOOKUP($C$1&"-"&$C13,rawdata!$E$3:$AC$14541,MATCH("hh_ls_data",rawdata!$E$3:$AC$3,0),0)), VLOOKUP($C$1&"-"&$C13,rawdata!$E$3:$AC$14541,MATCH("hh_ls_data",rawdata!$E$3:$AC$3,0),0), "") | H13: =IF(ISNUMBER(VLOOKUP($C$1&"-"&$C13,rawdata!$E$3:$AC$14541,MATCH("nfc_all_data",rawdata!$E$3:$AC$3,0),0)), VLOOKUP($C$1&"-"&$C13,rawdata!$E$3:$AC$14541,MATCH("nfc_all_data",rawdata!$E$3:$AC$3,0),0), "") | I13: =IF(ISNUMBER(VLOOKUP($C$1&"-"&$C13,rawdata!$E$3:$AC$14541,MATCH("nfc_ls_data",rawdata!$E$3:$AC$3,0),0)), VLOOKUP($C$1&"-"&$C13,rawdata!$E$3:$AC$14541,MATCH("nfc_ls_data",rawdata!$E$3:$AC$3,0),0), "") | J13: =IF(ISNUMBER(VLOOKUP($C$1&"-"&$C13,rawdata!$E$3:$AC$14541,MATCH("ps_data",rawdata!$E$3:$AC$3,0),0)), VLOOKUP($C$1&"-"&$C13,rawdata!$E$3:$AC$14541,MATCH("ps_data",rawdata!$E$3:$AC$3,0),0), "") | K13: =IF(ISNUMBER(VLOOKUP($C$1&"-"&$C13,rawdata!$E$3:$AC$14541,MATCH("nfps_data",rawdata!$E$3:$AC$3,0),0)), VLOOKUP($C$1&"-"&$C13,rawdata!$E$3:$AC$14541,MATCH("nfps_data",rawdata!$E$3:$AC$3,0),0), "") | L13: =IF(ISNUMBER(VLOOKUP($C$1&"-"&$C13,rawdata!$E$3:$AC$14541,MATCH("gg_data",rawdata!$E$3:$AC$3,0),0)), VLOOKUP($C$1&"-"&$C13,rawdata!$E$3:$AC$14541,MATCH("gg_data",rawdata!$E$3:$AC$3,0),0), "") | M13: =IF(ISNUMBER(VLOOKUP($C$1&"-"&$C13,rawdata!$E$3:$AC$14541,MATCH("cg_data",rawdata!$E$3:$AC$3,0),0)), VLOOKUP($C$1&"-"&$C13,rawdata!$E$3:$AC$14541,MATCH("cg_data",rawdata!$E$3:$AC$3,0),0), "") -> 25.177432 | N13: =IF(ISNUMBER(VLOOKUP($C$1&"-"&$C13,rawdata!$E$3:$AC$14541,MATCH("ngdp_data",rawdata!$E$3:$AC$3,0),0)), VLOOKUP($C$1&"-"&$C13,rawdata!$E$3:$AC$14541,MATCH("ngdp_data",rawdata!$E$3:$AC$3,0),0), "") -> 135.07774
C14: 1952 | D14: =IF(ISNUMBER(VLOOKUP($C$1&"-"&$C14,rawdata!$E$3:$AC$14541,MATCH("tot_all_data",rawdata!$E$3:$AC$3,0),0)), VLOOKUP($C$1&"-"&$C14,rawdata!$E$3:$AC$14541,MATCH("tot_all_data",rawdata!$E$3:$AC$3,0),0), "") | E14: =IF(ISNUMBER(VLOOKUP($C$1&"-"&$C14,rawdata!$E$3:$AC$14541,MATCH("tot_ls_data",rawdata!$E$3:$AC$3,0),0)), VLOOKUP($C$1&"-"&$C14,rawdata!$E$3:$AC$14541,MATCH("tot_ls_data",rawdata!$E$3:$AC$3,0),0), "") -> 16.752845 | F14: =IF(ISNUMBER(VLOOKUP($C$1&"-"&$C14,rawdata!$E$3:$AC$14541,MATCH("hh_all_data",rawdata!$E$3:$AC$3,0),0)), VLOOKUP($C$1&"-"&$C14,rawdata!$E$3:$AC$14541,MATCH("hh_all_data",rawdata!$E$3:$AC$3,0),0), "") | G14: =IF(ISNUMBER(VLOOKUP($C$1&"-"&$C14,rawdata!$E$3:$AC$14541,MATCH("hh_ls_data",rawdata!$E$3:$AC$3,0),0)), VLOOKUP($C$1&"-"&$C14,rawdata!$E$3:$AC$14541,MATCH("hh_ls_data",rawdata!$E$3:$AC$3,0),0), "") | H14: =IF(ISNUMBER(VLOOKUP($C$1&"-"&$C14,rawdata!$E$3:$AC$14541,MATCH("nfc_all_data",rawdata!$E$3:$AC$3,0),0)), VLOOKUP($C$1&"-"&$C14,rawdata!$E$3:$AC$14541,MATCH("nfc_all_data",rawdata!$E$3:$AC$3,0),0), "") | I14: =IF(ISNUMBER(VLOOKUP($C$1&"-"&$C14,rawdata!$E$3:$AC$14541,MATCH("nfc_ls_data",rawdata!$E$3:$AC$3,0),0)), VLOOKUP($C$1&"-"&$C14,rawdata!$E$3:$AC$14541,MATCH("nfc_ls_data",rawdata!$E$3:$AC$3,0),0), "") | J14: =IF(ISNUMBER(VLOOKUP($C$1&"-"&$C14,rawdata!$E$3:$AC$14541,MATCH("ps_data",rawdata!$E$3:$AC$3,0),0)), VLOOKUP($C$1&"-"&$C14,rawdata!$E$3:$AC$14541,MATCH("ps_data",rawdata!$E$3:$AC$3,0),0), "") | K14: =IF(ISNUMBER(VLOOKUP($C$1&"-"&$C14,rawdata!$E$3:$AC$14541,MATCH("nfps_data",rawdata!$E$3:$AC$3,0),0)), VLOOKUP($C$1&"-"&$C14,rawdata!$E$3:$AC$14541,MATCH("nfps_data",rawdata!$E$3:$AC$3,0),0), "") | L14: =IF(ISNUMBER(VLOOKUP($C$1&"-"&$C14,rawdata!$E$3:$AC$14541,MATCH("gg_data",rawdata!$E$3:$AC$3,0),0)), VLOOKUP($C$1&"-"&$C14,rawdata!$E$3:$AC$14541,MATCH("gg_data",rawdata!$E$3:$AC$3,0),0), "") | M14: =IF(ISNUMBER(VLOOKUP($C$1&"-"&$C14,rawdata!$E$3:$AC$14541,MATCH("cg_data",rawdata!$E$3:$AC$3,0),0)), VLOOKUP($C$1&"-"&$C14,rawdata!$E$3:$AC$14541,MATCH("cg_data",rawdata!$E$3:$AC$3,0),0), "") -> 26.388536 | N14: =IF(ISNUMBER(VLOOKUP($C$1&"-"&$C14,rawdata!$E$3:$AC$14541,MATCH("ngdp_data",rawdata!$E$3:$AC$3,0),0)), VLOOKUP($C$1&"-"&$C14,rawdata!$E$3:$AC$14541,MATCH("ngdp_data",rawdata!$E$3:$AC$3,0),0), "") -> 132.06115
C15: 1953 | D15: =IF(ISNUMBER(VLOOKUP($C$1&"-"&$C15,rawdata!$E$3:$AC$14541,MATCH("tot_all_data",rawdata!$E$3:$AC$3,0),0)), VLOOKUP($C$1&"-"&$C15,rawdata!$E$3:$AC$14541,MATCH("tot_all_data",rawdata!$E$3:$AC$3,0),0), "") | E15: =IF(ISNUMBER(VLOOKUP($C$1&"-"&$C15,rawdata!$E$3:$AC$14541,MATCH("tot_ls_data",rawdata!$E$3:$AC$3,0),0)), VLOOKUP($C$1&"-"&$C15,rawdata!$E$3:$AC$14541,MATCH("tot_ls_data",rawdata!$E$3:$AC$3,0),0), "") -> 16.203127 | F15: =IF(ISNUMBER(VLOOKUP($C$1&"-"&$C15,rawdata!$E$3:$AC$14541,MATCH("hh_all_data",rawdata!$E$3:$AC$3,0),0)), VLOOKUP($C$1&"-"&$C15,rawdata!$E$3:$AC$14541,MATCH("hh_all_data",rawdata!$E$3:$AC$3,0),0), "") | G15: =IF(ISNUMBER(VLOOKUP($C$1&"-"&$C15,rawdata!$E$3:$AC$14541,MATCH("hh_ls_data",rawdata!$E$3:$AC$3,0),0)), VLOOKUP($C$1&"-"&$C15,rawdata!$E$3:$AC$14541,MATCH("hh_ls_data",rawdata!$E$3:$AC$3,0),0), "") | H15: =IF(ISNUMBER(VLOOKUP($C$1&"-"&$C15,rawdata!$E$3:$AC$14541,MATCH("nfc_all_data",rawdata!$E$3:$AC$3,0),0)), VLOOKUP($C$1&"-"&$C15,rawdata!$E$3:$AC$14541,MATCH("nfc_all_data",rawdata!$E$3:$AC$3,0),0), "") | I15: =IF(ISNUMBER(VLOOKUP($C$1&"-"&$C15,rawdata!$E$3:$AC$14541,MATCH("nfc_ls_data",rawdata!$E$3:$AC$3,0),0)), VLOOKUP($C$1&"-"&$C15,rawdata!$E$3:$AC$14541,MATCH("nfc_ls_data",rawdata!$E$3:$AC$3,0),0), "") | J15: =IF(ISNUMBER(VLOOKUP($C$1&"-"&$C15,rawdata!$E$3:$AC$14541,MATCH("ps_data",rawdata!$E$3:$AC$3,0),0)), VLOOKUP($C$1&"-"&$C15,rawdata!$E$3:$AC$14541,MATCH("ps_data",rawdata!$E$3:$AC$3,0),0), "") | K15: =IF(ISNUMBER(VLOOKUP($C$1&"-"&$C15,rawdata!$E$3:$AC$14541,MATCH("nfps_data",rawdata!$E$3:$AC$3,0),0)), VLOOKUP($C$1&"-"&$C15,rawdata!$E$3:$AC$14541,MATCH("nfps_data",rawdata!$E$3:$AC$3,0),0), "") | L15: =IF(ISNUMBER(VLOOKUP($C$1&"-"&$C15,rawdata!$E$3:$AC$14541,MATCH("gg_data",rawdata!$E$3:$AC$3,0),0)), VLOOKUP($C$1&"-"&$C15,rawdata!$E$3:$AC$14541,MATCH("gg_data",rawdata!$E$3:$AC$3,0),0), "") | M15: =IF(ISNUMBER(VLOOKUP($C$1&"-"&$C15,rawdata!$E$3:$AC$14541,MATCH("cg_data",rawdata!$E$3:$AC$3,0),0)), VLOOKUP($C$1&"-"&$C15,rawdata!$E$3:$AC$14541,MATCH("cg_data",rawdata!$E$3:$AC$3,0),0), "") -> 24.646241 | N15: =IF(ISNUMBER(VLOOKUP($C$1&"-"&$C15,rawdata!$E$3:$AC$14541,MATCH("ngdp_data",rawdata!$E$3:$AC$3,0),0)), VLOOKUP($C$1&"-"&$C15,rawdata!$E$3:$AC$14541,MATCH("ngdp_data",rawdata!$E$3:$AC$3,0),0), "") -> 139.64589
C16: 1954 | D16: =IF(ISNUMBER(VLOOKUP($C$1&"-"&$C16,rawdata!$E$3:$AC$14541,MATCH("tot_all_data",rawdata!$E$3:$AC$3,0),0)), VLOOKUP($C$1&"-"&$C16,rawdata!$E$3:$AC$14541,MATCH("tot_all_data",rawdata!$E$3:$AC$3,0),0), "") | E16: =IF(ISNUMBER(VLOOKUP($C$1&"-"&$C16,rawdata!$E$3:$AC$14541,MATCH("tot_ls_data",rawdata!$E$3:$AC$3,0),0)), VLOOKUP($C$1&"-"&$C16,rawdata!$E$3:$AC$14541,MATCH("tot_ls_data",rawdata!$E$3:$AC$3,0),0), "") -> 18.649235 | F16: =IF(ISNUMBER(VLOOKUP($C$1&"-"&$C16,rawdata!$E$3:$AC$14541,MATCH("hh_all_data",rawdata!$E$3:$AC$3,0),0)), VLOOKUP($C$1&"-"&$C16,rawdata!$E$3:$AC$14541,MATCH("hh_all_data",rawdata!$E$3:$AC$3,0),0), "") | G16: =IF(ISNUMBER(VLOOKUP($C$1&"-"&$C16,rawdata!$E$3:$AC$14541,MATCH("hh_ls_data",rawdata!$E$3:$AC$3,0),0)), VLOOKUP($C$1&"-"&$C16,rawdata!$E$3:$AC$14541,MATCH("hh_ls_data",rawdata!$E$3:$AC$3,0),0), "") | H16: =IF(ISNUMBER(VLOOKUP($C$1&"-"&$C16,rawdata!$E$3:$AC$14541,MATCH("nfc_all_data",rawdata!$E$3:$AC$3,0),0)), VLOOKUP($C$1&"-"&$C16,rawdata!$E$3:$AC$14541,MATCH("nfc_all_data",rawdata!$E$3:$AC$3,0),0), "") | I16: =IF(ISNUMBER(VLOOKUP($C$1&"-"&$C16,rawdata!$E$3:$AC$14541,MATCH("nfc_ls_data",rawdata!$E$3:$AC$3,0),0)), VLOOKUP($C$1&"-"&$C16,rawdata!$E$3:$AC$14541,MATCH("nfc_ls_data",rawdata!$E$3:$AC$3,0),0), "") | J16: =IF(ISNUMBER(VLOOKUP($C$1&"-"&$C16,rawdata!$E$3:$AC$14541,MATCH("ps_data",rawdata!$E$3:$AC$3,0),0)), VLOOKUP($C$1&"-"&$C16,rawdata!$E$3:$AC$14541,MATCH("ps_data",rawdata!$E$3:$AC$3,0),0), "") | K16: =IF(ISNUMBER(VLOOKUP($C$1&"-"&$C16,rawdata!$E$3:$AC$14541,MATCH("nfps_data",rawdata!$E$3:$AC$3,0),0)), VLOOKUP($C$1&"-"&$C16,rawdata!$E$3:$AC$14541,MATCH("nfps_data",rawdata!$E$3:$AC$3,0),0), "") | L16: =IF(ISNUMBER(VLOOKUP($C$1&"-"&$C16,rawdata!$E$3:$AC$14541,MATCH("gg_data",rawdata!$E$3:$AC$3,0),0)), VLOOKUP($C$1&"-"&$C16,rawdata!$E$3:$AC$14541,MATCH("gg_data",rawdata!$E$3:$AC$3,0),0), "") | M16: =IF(ISNUMBER(VLOOKUP($C$1&"-"&$C16,rawdata!$E$3:$AC$14541,MATCH("cg_data",rawdata!$E$3:$AC$3,0),0)), VLOOKUP($C$1&"-"&$C16,rawdata!$E$3:$AC$14541,MATCH("cg_data",rawdata!$E$3:$AC$3,0),0), "") -> 24.862066 | N16: =IF(ISNUMBER(VLOOKUP($C$1&"-"&$C16,rawdata!$E$3:$AC$14541,MATCH("ngdp_data",rawdata!$E$3:$AC$3,0),0)), VLOOKUP($C$1&"-"&$C16,rawdata!$E$3:$AC$14541,MATCH("ngdp_data",rawdata!$E$3:$AC$3,0),0), "") -> 130.44503
C17: 1955 | D17: =IF(ISNUMBER(VLOOKUP($C$1&"-"&$C17,rawdata!$E$3:$AC$14541,MATCH("tot_all_data",rawdata!$E$3:$AC$3,0),0)), VLOOKUP($C$1&"-"&$C17,rawdata!$E$3:$AC$14541,MATCH("tot_all_data",rawdata!$E$3:$AC$3,0),0), "") | E17: =IF(ISNUMBER(VLOOKUP($C$1&"-"&$C17,rawdata!$E$3:$AC$14541,MATCH("tot_ls_data",rawdata!$E$3:$AC$3,0),0)), VLOOKUP($C$1&"-"&$C17,rawdata!$E$3:$AC$14541,MATCH("tot_ls_data",rawdata!$E$3:$AC$3,0),0), "") -> 19.907652 | F17: =IF(ISNUMBER(VLOOKUP($C$1&"-"&$C17,rawdata!$E$3:$AC$14541,MATCH("hh_all_data",rawdata!$E$3:$AC$3,0),0)), VLOOKUP($C$1&"-"&$C17,rawdata!$E$3:$AC$14541,MATCH("hh_all_data",rawdata!$E$3:$AC$3,0),0), "") | G17: =IF(ISNUMBER(VLOOKUP($C$1&"-"&$C17,rawdata!$E$3:$AC$14541,MATCH("hh_ls_data",rawdata!$E$3:$AC$3,0),0)), VLOOKUP($C$1&"-"&$C17,rawdata!$E$3:$AC$14541,MATCH("hh_ls_data",rawdata!$E$3:$AC$3,0),0), "") | H17: =IF(ISNUMBER(VLOOKUP($C$1&"-"&$C17,rawdata!$E$3:$AC$14541,MATCH("nfc_all_data",rawdata!$E$3:$AC$3,0),0)), VLOOKUP($C$1&"-"&$C17,rawdata!$E$3:$AC$14541,MATCH("nfc_all_data",rawdata!$E$3:$AC$3,0),0), "") | I17: =IF(ISNUMBER(VLOOKUP($C$1&"-"&$C17,rawdata!$E$3:$AC$14541,MATCH("nfc_ls_data",rawdata!$E$3:$AC$3,0),0)), VLOOKUP($C$1&"-"&$C17,rawdata!$E$3:$AC$14541,MATCH("nfc_ls_data",rawdata!$E$3:$AC$3,0),0), "") | J17: =IF(ISNUMBER(VLOOKUP($C$1&"-"&$C17,rawdata!$E$3:$AC$14541,MATCH("ps_data",rawdata!$E$3:$AC$3,0),0)), VLOOKUP($C$1&"-"&$C17,rawdata!$E$3:$AC$14541,MATCH("ps_data",rawdata!$E$3:$AC$3,0),0), "") | K17: =IF(ISNUMBER(VLOOKUP($C$1&"-"&$C17,rawdata!$E$3:$AC$14541,MATCH("nfps_data",rawdata!$E$3:$AC$3,0),0)), VLOOKUP($C$1&"-"&$C17,rawdata!$E$3:$AC$14541,MATCH("nfps_data",rawdata!$E$3:$AC$3,0),0), "") | L17: =IF(ISNUMBER(VLOOKUP($C$1&"-"&$C17,rawdata!$E$3:$AC$14541,MATCH("gg_data",rawdata!$E$3:$AC$3,0),0)), VLOOKUP($C$1&"-"&$C17,rawdata!$E$3:$AC$14541,MATCH("gg_data",rawdata!$E$3:$AC$3,0),0), "") | M17: =IF(ISNUMBER(VLOOKUP($C$1&"-"&$C17,rawdata!$E$3:$AC$14541,MATCH("cg_data",rawdata!$E$3:$AC$3,0),0)), VLOOKUP($C$1&"-"&$C17,rawdata!$E$3:$AC$14541,MATCH("cg_data",rawdata!$E$3:$AC$3,0),0), "") -> 29.625378 | N17: =IF(ISNUMBER(VLOOKUP($C$1&"-"&$C17,rawdata!$E$3:$AC$14541,MATCH("ngdp_data",rawdata!$E$3:$AC$3,0),0)), VLOOKUP($C$1&"-"&$C17,rawdata!$E$3:$AC$14541,MATCH("ngdp_data",rawdata!$E$3:$AC$3,0),0), "") -> 136.4852
C18: 1956 | D18: =IF(ISNUMBER(VLOOKUP($C$1&"-"&$C18,rawdata!$E$3:$AC$14541,MATCH("tot_all_data",rawdata!$E$3:$AC$3,0),0)), VLOOKUP($C$1&"-"&$C18,rawdata!$E$3:$AC$14541,MATCH("tot_all_data",rawdata!$E$3:$AC$3,0),0), "") | E18: =IF(ISNUMBER(VLOOKUP($C$1&"-"&$C18,rawdata!$E$3:$AC$14541,MATCH("tot_ls_data",rawdata!$E$3:$AC$3,0),0)), VLOOKUP($C$1&"-"&$C18,rawdata!$E$3:$AC$14541,MATCH("tot_ls_data",rawdata!$E$3:$AC$3,0),0), "") -> 18.87129 | F18: =IF(ISNUMBER(VLOOKUP($C$1&"-"&$C18,rawdata!$E$3:$AC$14541,MATCH("hh_all_data",rawdata!$E$3:$AC$3,0),0)), VLOOKUP($C$1&"-"&$C18,rawdata!$E$3:$AC$14541,MATCH("hh_all_data",rawdata!$E$3:$AC$3,0),0), "") | G18: =IF(ISNUMBER(VLOOKUP($C$1&"-"&$C18,rawdata!$E$3:$AC$14541,MATCH("hh_ls_data",rawdata!$E$3:$AC$3,0),0)), VLOOKUP($C$1&"-"&$C18,rawdata!$E$3:$AC$14541,MATCH("hh_ls_data",rawdata!$E$3:$AC$3,0),0), "") | H18: =IF(ISNUMBER(VLOOKUP($C$1&"-"&$C18,rawdata!$E$3:$AC$14541,MATCH("nfc_all_data",rawdata!$E$3:$AC$3,0),0)), VLOOKUP($C$1&"-"&$C18,rawdata!$E$3:$AC$14541,MATCH("nfc_all_data",rawdata!$E$3:$AC$3,0),0), "") | I18: =IF(ISNUMBER(VLOOKUP($C$1&"-"&$C18,rawdata!$E$3:$AC$14541,MATCH("nfc_ls_data",rawdata!$E$3:$AC$3,0),0)), VLOOKUP($C$1&"-"&$C18,rawdata!$E$3:$AC$14541,MATCH("nfc_ls_data",rawdata!$E$3:$AC$3,0),0), "") | J18: =IF(ISNUMBER(VLOOKUP($C$1&"-"&$C18,rawdata!$E$3:$AC$14541,MATCH("ps_data",rawdata!$E$3:$AC$3,0),0)), VLOOKUP($C$1&"-"&$C18,rawdata!$E$3:$AC$14541,MATCH("ps_data",rawdata!$E$3:$AC$3,0),0), "") | K18: =IF(ISNUMBER(VLOOKUP($C$1&"-"&$C18,rawdata!$E$3:$AC$14541,MATCH("nfps_data",rawdata!$E$3:$AC$3,0),0)), VLOOKUP($C$1&"-"&$C18,rawdata!$E$3:$AC$14541,MATCH("nfps_data",rawdata!$E$3:$AC$3,0),0), "") | L18: =IF(ISNUMBER(VLOOKUP($C$1&"-"&$C18,rawdata!$E$3:$AC$14541,MATCH("gg_data",rawdata!$E$3:$AC$3,0),0)), VLOOKUP($C$1&"-"&$C18,rawdata!$E$3:$AC$14541,MATCH("gg_data",rawdata!$E$3:$AC$3,0),0), "") | M18: =IF(ISNUMBER(VLOOKUP($C$1&"-"&$C18,rawdata!$E$3:$AC$14541,MATCH("cg_data",rawdata!$E$3:$AC$3,0),0)), VLOOKUP($C$1&"-"&$C18,rawdata!$E$3:$AC$14541,MATCH("cg_data",rawdata!$E$3:$AC$3,0),0), "") -> 25.479542 | N18: =IF(ISNUMBER(VLOOKUP($C$1&"-"&$C18,rawdata!$E$3:$AC$14541,MATCH("ngdp_data",rawdata!$E$3:$AC$3,0),0)), VLOOKUP($C$1&"-"&$C18,rawdata!$E$3:$AC$14541,MATCH("ngdp_data",rawdata!$E$3:$AC$3,0),0), "") -> 154.1813
C19: 1957 | D19: =IF(ISNUMBER(VLOOKUP($C$1&"-"&$C19,rawdata!$E$3:$AC$14541,MATCH("tot_all_data",rawdata!$E$3:$AC$3,0),0)), VLOOKUP($C$1&"-"&$C19,rawdata!$E$3:$AC$14541,MATCH("tot_all_data",rawdata!$E$3:$AC$3,0),0), "") | E19: =IF(ISNUMBER(VLOOKUP($C$1&"-"&$C19,rawdata!$E$3:$AC$14541,MATCH("tot_ls_data",rawdata!$E$3:$AC$3,0),0)), VLOOKUP($C$1&"-"&$C19,rawdata!$E$3:$AC$14541,MATCH("tot_ls_data",rawdata!$E$3:$AC$3,0),0), "") -> 20.477868 | F19: =IF(ISNUMBER(VLOOKUP($C$1&"-"&$C19,rawdata!$E$3:$AC$14541,MATCH("hh_all_data",rawdata!$E$3:$AC$3,0),0)), VLOOKUP($C$1&"-"&$C19,rawdata!$E$3:$AC$14541,MATCH("hh_all_data",rawdata!$E$3:$AC$3,0),0), "") | G19: =IF(ISNUMBER(VLOOKUP($C$1&"-"&$C19,rawdata!$E$3:$AC$14541,MATCH("hh_ls_data",rawdata!$E$3:$AC$3,0),0)), VLOOKUP($C$1&"-"&$C19,rawdata!$E$3:$AC$14541,MATCH("hh_ls_data",rawdata!$E$3:$AC$3,0),0), "") | H19: =IF(ISNUMBER(VLOOKUP($C$1&"-"&$C19,rawdata!$E$3:$AC$14541,MATCH("nfc_all_data",rawdata!$E$3:$AC$3,0),0)), VLOOKUP($C$1&"-"&$C19,rawdata!$E$3:$AC$14541,MATCH("nfc_all_data",rawdata!$E$3:$AC$3,0),0), "") | I19: =IF(ISNUMBER(VLOOKUP($C$1&"-"&$C19,rawdata!$E$3:$AC$14541,MATCH("nfc_ls_data",rawdata!$E$3:$AC$3,0),0)), VLOOKUP($C$1&"-"&$C19,rawdata!$E$3:$AC$14541,MATCH("nfc_ls_data",rawdata!$E$3:$AC$3,0),0), "") | J19: =IF(ISNUMBER(VLOOKUP($C$1&"-"&$C19,rawdata!$E$3:$AC$14541,MATCH("ps_data",rawdata!$E$3:$AC$3,0),0)), VLOOKUP($C$1&"-"&$C19,rawdata!$E$3:$AC$14541,MATCH("ps_data",rawdata!$E$3:$AC$3,0),0), "") | K19: =IF(ISNUMBER(VLOOKUP($C$1&"-"&$C19,rawdata!$E$3:$AC$14541,MATCH("nfps_data",rawdata!$E$3:$AC$3,0),0)), VLOOKUP($C$1&"-"&$C19,rawdata!$E$3:$AC$14541,MATCH("nfps_data",rawdata!$E$3:$AC$3,0),0), "") | L19: =IF(ISNUMBER(VLOOKUP($C$1&"-"&$C19,rawdata!$E$3:$AC$14541,MATCH("gg_data",rawdata!$E$3:$AC$3,0),0)), VLOOKUP($C$1&"-"&$C19,rawdata!$E$3:$AC$14541,MATCH("gg_data",rawdata!$E$3:$AC$3,0),0), "") | M19: =IF(ISNUMBER(VLOOKUP($C$1&"-"&$C19,rawdata!$E$3:$AC$14541,MATCH("cg_data",rawdata!$E$3:$AC$3,0),0)), VLOOKUP($C$1&"-"&$C19,rawdata!$E$3:$AC$14541,MATCH("cg_data",rawdata!$E$3:$AC$3,0),0), "") -> 27.38254 | N19: =IF(ISNUMBER(VLOOKUP($C$1&"-"&$C19,rawdata!$E$3:$AC$14541,MATCH("ngdp_data",rawdata!$E$3:$AC$3,0),0)), VLOOKUP($C$1&"-"&$C19,rawdata!$E$3:$AC$14541,MATCH("ngdp_data",rawdata!$E$3:$AC$3,0),0), "") -> 156.33952
C20: 1958 | D20: =IF(ISNUMBER(VLOOKUP($C$1&"-"&$C20,rawdata!$E$3:$AC$14541,MATCH("tot_all_data",rawdata!$E$3:$AC$3,0),0)), VLOOKUP($C$1&"-"&$C20,rawdata!$E$3:$AC$14541,MATCH("tot_all_data",rawdata!$E$3:$AC$3,0),0), "") | E20: =IF(ISNUMBER(VLOOKUP($C$1&"-"&$C20,rawdata!$E$3:$AC$14541,MATCH("tot_ls_data",rawdata!$E$3:$AC$3,0),0)), VLOOKUP($C$1&"-"&$C20,rawdata!$E$3:$AC$14541,MATCH("tot_ls_data",rawdata!$E$3:$AC$3,0),0), "") -> 20.375366 | F20: =IF(ISNUMBER(VLOOKUP($C$1&"-"&$C20,rawdata!$E$3:$AC$14541,MATCH("hh_all_data",rawdata!$E$3:$AC$3,0),0)), VLOOKUP($C$1&"-"&$C20,rawdata!$E$3:$AC$14541,MATCH("hh_all_data",rawdata!$E$3:$AC$3,0),0), "") | G20: =IF(ISNUMBER(VLOOKUP($C$1&"-"&$C20,rawdata!$E$3:$AC$14541,MATCH("hh_ls_data",rawdata!$E$3:$AC$3,0),0)), VLOOKUP($C$1&"-"&$C20,rawdata!$E$3:$AC$14541,MATCH("hh_ls_data",rawdata!$E$3:$AC$3,0),0), "") | H20: =IF(ISNUMBER(VLOOKUP($C$1&"-"&$C20,rawdata!$E$3:$AC$14541,MATCH("nfc_all_data",rawdata!$E$3:$AC$3,0),0)), VLOOKUP($C$1&"-"&$C20,rawdata!$E$3:$AC$14541,MATCH("nfc_all_data",rawdata!$E$3:$AC$3,0),0), "") | I20: =IF(ISNUMBER(VLOOKUP($C$1&"-"&$C20,rawdata!$E$3:$AC$14541,MATCH("nfc_ls_data",rawdata!$E$3:$AC$3,0),0)), VLOOKUP($C$1&"-"&$C20,rawdata!$E$3:$AC$14541,MATCH("nfc_ls_data",rawdata!$E$3:$AC$3,0),0), "") | J20: =IF(ISNUMBER(VLOOKUP($C$1&"-"&$C20,rawdata!$E$3:$AC$14541,MATCH("ps_data",rawdata!$E$3:$AC$3,0),0)), VLOOKUP($C$1&"-"&$C20,rawdata!$E$3:$AC$14541,MATCH("ps_data",rawdata!$E$3:$AC$3,0),0), "") | K20: =IF(ISNUMBER(VLOOKUP($C$1&"-"&$C20,rawdata!$E$3:$AC$14541,MATCH("nfps_data",rawdata!$E$3:$AC$3,0),0)), VLOOKUP($C$1&"-"&$C20,rawdata!$E$3:$AC$14541,MATCH("nfps_data",rawdata!$E$3:$AC$3,0),0), "") | L20: =IF(ISNUMBER(VLOOKUP($C$1&"-"&$C20,rawdata!$E$3:$AC$14541,MATCH("gg_data",rawdata!$E$3:$AC$3,0),0)), VLOOKUP($C$1&"-"&$C20,rawdata!$E$3:$AC$14541,MATCH("gg_data",rawdata!$E$3:$AC$3,0),0), "") | M20: =IF(ISNUMBER(VLOOKUP($C$1&"-"&$C20,rawdata!$E$3:$AC$14541,MATCH("cg_data",rawdata!$E$3:$AC$3,0),0)), VLOOKUP($C$1&"-"&$C20,rawdata!$E$3:$AC$14541,MATCH("cg_data",rawdata!$E$3:$AC$3,0),0), "") -> 23.732237 | N20: =IF(ISNUMBER(VLOOKUP($C$1&"-"&$C20,rawdata!$E$3:$AC$14541,MATCH("ngdp_data",rawdata!$E$3:$AC$3,0),0)), VLOOKUP($C$1&"-"&$C20,rawdata!$E$3:$AC$14541,MATCH("ngdp_data",rawdata!$E$3:$AC$3,0),0), "") -> 172.45334
C21: 1959 | D21: =IF(ISNUMBER(VLOOKUP($C$1&"-"&$C21,rawdata!$E$3:$AC$14541,MATCH("tot_all_data",rawdata!$E$3:$AC$3,0),0)), VLOOKUP($C$1&"-"&$C21,rawdata!$E$3:$AC$14541,MATCH("tot_all_data",rawdata!$E$3:$AC$3,0),0), "") | E21: =IF(ISNUMBER(VLOOKUP($C$1&"-"&$C21,rawdata!$E$3:$AC$14541,MATCH("tot_ls_data",rawdata!$E$3:$AC$3,0),0)), VLOOKUP($C$1&"-"&$C21,rawdata!$E$3:$AC$14541,MATCH("tot_ls_data",rawdata!$E$3:$AC$3,0),0), "") -> 22.423418 | F21: =IF(ISNUMBER(VLOOKUP($C$1&"-"&$C21,rawdata!$E$3:$AC$14541,MATCH("hh_all_data",rawdata!$E$3:$AC$3,0),0)), VLOOKUP($C$1&"-"&$C21,rawdata!$E$3:$AC$14541,MATCH("hh_all_data",rawdata!$E$3:$AC$3,0),0), "") | G21: =IF(ISNUMBER(VLOOKUP($C$1&"-"&$C21,rawdata!$E$3:$AC$14541,MATCH("hh_ls_data",rawdata!$E$3:$AC$3,0),0)), VLOOKUP($C$1&"-"&$C21,rawdata!$E$3:$AC$14541,MATCH("hh_ls_data",rawdata!$E$3:$AC$3,0),0), "") | H21: =IF(ISNUMBER(VLOOKUP($C$1&"-"&$C21,rawdata!$E$3:$AC$14541,MATCH("nfc_all_data",rawdata!$E$3:$AC$3,0),0)), VLOOKUP($C$1&"-"&$C21,rawdata!$E$3:$AC$14541,MATCH("nfc_all_data",rawdata!$E$3:$AC$3,0),0), "") | I21: =IF(ISNUMBER(VLOOKUP($C$1&"-"&$C21,rawdata!$E$3:$AC$14541,MATCH("nfc_ls_data",rawdata!$E$3:$AC$3,0),0)), VLOOKUP($C$1&"-"&$C21,rawdata!$E$3:$AC$14541,MATCH("nfc_ls_data",rawdata!$E$3:$AC$3,0),0), "") | J21: =IF(ISNUMBER(VLOOKUP($C$1&"-"&$C21,rawdata!$E$3:$AC$14541,MATCH("ps_data",rawdata!$E$3:$AC$3,0),0)), VLOOKUP($C$1&"-"&$C21,rawdata!$E$3:$AC$14541,MATCH("ps_data",rawdata!$E$3:$AC$3,0),0), "") | K21: =IF(ISNUMBER(VLOOKUP($C$1&"-"&$C21,rawdata!$E$3:$AC$14541,MATCH("nfps_data",rawdata!$E$3:$AC$3,0),0)), VLOOKUP($C$1&"-"&$C21,rawdata!$E$3:$AC$14541,MATCH("nfps_data",rawdata!$E$3:$AC$3,0),0), "") | L21: =IF(ISNUMBER(VLOOKUP($C$1&"-"&$C21,rawdata!$E$3:$AC$14541,MATCH("gg_data",rawdata!$E$3:$AC$3,0),0)), VLOOKUP($C$1&"-"&$C21,rawdata!$E$3:$AC$14541,MATCH("gg_data",rawdata!$E$3:$AC$3,0),0), "") | M21: =IF(ISNUMBER(VLOOKUP($C$1&"-"&$C21,rawdata!$E$3:$AC$14541,MATCH("cg_data",rawdata!$E$3:$AC$3,0),0)), VLOOKUP($C$1&"-"&$C21,rawdata!$E$3:$AC$14541,MATCH("cg_data",rawdata!$E$3:$AC$3,0),0), "") -> 33.584855 | N21: =IF(ISNUMBER(VLOOKUP($C$1&"-"&$C21,rawdata!$E$3:$AC$14541,MATCH("ngdp_data",rawdata!$E$3:$AC$3,0),0)), VLOOKUP($C$1&"-"&$C21,rawdata!$E$3:$AC$14541,MATCH("ngdp_data",rawdata!$E$3:$AC$3,0),0), "") -> 175.82511
C22: 1960 | D22: =IF(ISNUMBER(VLOOKUP($C$1&"-"&$C22,rawdata!$E$3:$AC$14541,MATCH("tot_all_data",rawdata!$E$3:$AC$3,0),0)), VLOOKUP($C$1&"-"&$C22,rawdata!$E$3:$AC$14541,MATCH("tot_all_data",rawdata!$E$3:$AC$3,0),0), "") | E22: =IF(ISNUMBER(VLOOKUP($C$1&"-"&$C22,rawdata!$E$3:$AC$14541,MATCH("tot_ls_data",rawdata!$E$3:$AC$3,0),0)), VLOOKUP($C$1&"-"&$C22,rawdata!$E$3:$AC$14541,MATCH("tot_ls_data",rawdata!$E$3:$AC$3,0),0), "") -> 22.792877 | F22: =IF(ISNUMBER(VLOOKUP($C$1&"-"&$C22,rawdata!$E$3:$AC$14541,MATCH("hh_all_data",rawdata!$E$3:$AC$3,0),0)), VLOOKUP($C$1&"-"&$C22,rawdata!$E$3:$AC$14541,MATCH("hh_all_data",rawdata!$E$3:$AC$3,0),0), "") | G22: =IF(ISNUMBER(VLOOKUP($C$1&"-"&$C22,rawdata!$E$3:$AC$14541,MATCH("hh_ls_data",rawdata!$E$3:$AC$3,0),0)), VLOOKUP($C$1&"-"&$C22,rawdata!$E$3:$AC$14541,MATCH("hh_ls_data",rawdata!$E$3:$AC$3,0),0), "") | H22: =IF(ISNUMBER(VLOOKUP($C$1&"-"&$C22,rawdata!$E$3:$AC$14541,MATCH("nfc_all_data",rawdata!$E$3:$AC$3,0),0)), VLOOKUP($C$1&"-"&$C22,rawdata!$E$3:$AC$14541,MATCH("nfc_all_data",rawdata!$E$3:$AC$3,0),0), "") | I22: =IF(ISNUMBER(VLOOKUP($C$1&"-"&$C22,rawdata!$E$3:$AC$14541,MATCH("nfc_ls_data",rawdata!$E$3:$AC$3,0),0)), VLOOKUP($C$1&"-"&$C22,rawdata!$E$3:$AC$14541,MATCH("nfc_ls_data",rawdata!$E$3:$AC$3,0),0), "") | J22: =IF(ISNUMBER(VLOOKUP($C$1&"-"&$C22,rawdata!$E$3:$AC$14541,MATCH("ps_data",rawdata!$E$3:$AC$3,0),0)), VLOOKUP($C$1&"-"&$C22,rawdata!$E$3:$AC$14541,MATCH("ps_data",rawdata!$E$3:$AC$3,0),0), "") | K22: =IF(ISNUMBER(VLOOKUP($C$1&"-"&$C22,rawdata!$E$3:$AC$14541,MATCH("nfps_data",rawdata!$E$3:$AC$3,0),0)), VLOOKUP($C$1&"-"&$C22,rawdata!$E$3:$AC$14541,MATCH("nfps_data",rawdata!$E$3:$AC$3,0),0), "") | L22: =IF(ISNUMBER(VLOOKUP($C$1&"-"&$C22,rawdata!$E$3:$AC$14541,MATCH("gg_data",rawdata!$E$3:$AC$3,0),0)), VLOOKUP($C$1&"-"&$C22,rawdata!$E$3:$AC$14541,MATCH("gg_data",rawdata!$E$3:$AC$3,0),0), "") | M22: =IF(ISNUMBER(VLOOKUP($C$1&"-"&$C22,rawdata!$E$3:$AC$14541,MATCH("cg_data",rawdata!$E$3:$AC$3,0),0)), VLOOKUP($C$1&"-"&$C22,rawdata!$E$3:$AC$14541,MATCH("cg_data",rawdata!$E$3:$AC$3,0),0), "") -> 34.458642 | N22: =IF(ISNUMBER(VLOOKUP($C$1&"-"&$C22,rawdata!$E$3:$AC$14541,MATCH("ngdp_data",rawdata!$E$3:$AC$3,0),0)), VLOOKUP($C$1&"-"&$C22,rawdata!$E$3:$AC$14541,MATCH("ngdp_data",rawdata!$E$3:$AC$3,0),0), "") -> 180.34143
C23: 1961 | D23: =IF(ISNUMBER(VLOOKUP($C$1&"-"&$C23,rawdata!$E$3:$AC$14541,MATCH("tot_all_data",rawdata!$E$3:$AC$3,0),0)), VLOOKUP($C$1&"-"&$C23,rawdata!$E$3:$AC$14541,MATCH("tot_all_data",rawdata!$E$3:$AC$3,0),0), "") | E23: =IF(ISNUMBER(VLOOKUP($C$1&"-"&$C23,rawdata!$E$3:$AC$14541,MATCH("tot_ls_data",rawdata!$E$3:$AC$3,0),0)), VLOOKUP($C$1&"-"&$C23,rawdata!$E$3:$AC$14541,MATCH("tot_ls_data",rawdata!$E$3:$AC$3,0),0), "") -> 22.458604 | F23: =IF(ISNUMBER(VLOOKUP($C$1&"-"&$C23,rawdata!$E$3:$AC$14541,MATCH("hh_all_data",rawdata!$E$3:$AC$3,0),0)), VLOOKUP($C$1&"-"&$C23,rawdata!$E$3:$AC$14541,MATCH("hh_all_data",rawdata!$E$3:$AC$3,0),0), "") | G23: =IF(ISNUMBER(VLOOKUP($C$1&"-"&$C23,rawdata!$E$3:$AC$14541,MATCH("hh_ls_data",rawdata!$E$3:$AC$3,0),0)), VLOOKUP($C$1&"-"&$C23,rawdata!$E$3:$AC$14541,MATCH("hh_ls_data",rawdata!$E$3:$AC$3,0),0), "") | H23: =IF(ISNUMBER(VLOOKUP($C$1&"-"&$C23,rawdata!$E$3:$AC$14541,MATCH("nfc_all_data",rawdata!$E$3:$AC$3,0),0)), VLOOKUP($C$1&"-"&$C23,rawdata!$E$3:$AC$14541,MATCH("nfc_all_data",rawdata!$E$3:$AC$3,0),0), "") | I23: =IF(ISNUMBER(VLOOKUP($C$1&"-"&$C23,rawdata!$E$3:$AC$14541,MATCH("nfc_ls_data",rawdata!$E$3:$AC$3,0),0)), VLOOKUP($C$1&"-"&$C23,rawdata!$E$3:$AC$14541,MATCH("nfc_ls_data",rawdata!$E$3:$AC$3,0),0), "") | J23: =IF(ISNUMBER(VLOOKUP($C$1&"-"&$C23,rawdata!$E$3:$AC$14541,MATCH("ps_data",rawdata!$E$3:$AC$3,0),0)), VLOOKUP($C$1&"-"&$C23,rawdata!$E$3:$AC$14541,MATCH("ps_data",rawdata!$E$3:$AC$3,0),0), "") | K23: =IF(ISNUMBER(VLOOKUP($C$1&"-"&$C23,rawdata!$E$3:$AC$14541,MATCH("nfps_data",rawdata!$E$3:$AC$3,0),0)), VLOOKUP($C$1&"-"&$C23,rawdata!$E$3:$AC$14541,MATCH("nfps_data",rawdata!$E$3:$AC$3,0),0), "") | L23: =IF(ISNUMBER(VLOOKUP($C$1&"-"&$C23,rawdata!$E$3:$AC$14541,MATCH("gg_data",rawdata!$E$3:$AC$3,0),0)), VLOOKUP($C$1&"-"&$C23,rawdata!$E$3:$AC$14541,MATCH("gg_data",rawdata!$E$3:$AC$3,0),0), "") | M23: =IF(ISNUMBER(VLOOKUP($C$1&"-"&$C23,rawdata!$E$3:$AC$14541,MATCH("cg_data",rawdata!$E$3:$AC$3,0),0)), VLOOKUP($C$1&"-"&$C23,rawdata!$E$3:$AC$14541,MATCH("cg_data",rawdata!$E$3:$AC$3,0),0), "") -> 36.78929 | N23: =IF(ISNUMBER(VLOOKUP($C$1&"-"&$C23,rawdata!$E$3:$AC$14541,MATCH("ngdp_data",rawdata!$E$3:$AC$3,0),0)), VLOOKUP($C$1&"-"&$C23,rawdata!$E$3:$AC$14541,MATCH("ngdp_data",rawdata!$E$3:$AC$3,0),0), "") -> 190.26116
... C86: 2024 | D86: =IF(ISNUMBER(VLOOKUP($C$1&"-"&$C86,rawdata!$E$3:$AC$14541,MATCH("tot_all_data",rawdata!$E$3:$AC$3,0),0)), VLOOKUP($C$1&"-"&$C86,rawdata!$E$3:$AC$14541,MATCH("tot_all_data",rawdata!$E$3:$AC$3,0),0), "") | E86: =IF(ISNUMBER(VLOOKUP($C$1&"-"&$C86,rawdata!$E$3:$AC$14541,MATCH("tot_ls_data",rawdata!$E$3:$AC$3,0),0)), VLOOKUP($C$1&"-"&$C86,rawdata!$E$3:$AC$14541,MATCH("tot_ls_data",rawdata!$E$3:$AC$3,0),0), "") -> 90.550387 | F86: =IF(ISNUMBER(VLOOKUP($C$1&"-"&$C86,rawdata!$E$3:$AC$14541,MATCH("hh_all_data",rawdata!$E$3:$AC$3,0),0)), VLOOKUP($C$1&"-"&$C86,rawdata!$E$3:$AC$14541,MATCH("hh_all_data",rawdata!$E$3:$AC$3,0),0), "") | G86: =IF(ISNUMBER(VLOOKUP($C$1&"-"&$C86,rawdata!$E$3:$AC$14541,MATCH("hh_ls_data",rawdata!$E$3:$AC$3,0),0)), VLOOKUP($C$1&"-"&$C86,rawdata!$E$3:$AC$14541,MATCH("hh_ls_data",rawdata!$E$3:$AC$3,0),0), "") -> 40.768391 | H86: =IF(ISNUMBER(VLOOKUP($C$1&"-"&$C86,rawdata!$E$3:$AC$14541,MATCH("nfc_all_data",rawdata!$E$3:$AC$3,0),0)), VLOOKUP($C$1&"-"&$C86,rawdata!$E$3:$AC$14541,MATCH("nfc_all_data",rawdata!$E$3:$AC$3,0),0), "") | I86: =IF(ISNUMBER(VLOOKUP($C$1&"-"&$C86,rawdata!$E$3:$AC$14541,MATCH("nfc_ls_data",rawdata!$E$3:$AC$3,0),0)), VLOOKUP($C$1&"-"&$C86,rawdata!$E$3:$AC$14541,MATCH("nfc_ls_data",rawdata!$E$3:$AC$3,0),0), "") -> 49.781996 | J86: =IF(ISNUMBER(VLOOKUP($C$1&"-"&$C86,rawdata!$E$3:$AC$14541,MATCH("ps_data",rawdata!$E$3:$AC$3,0),0)), VLOOKUP($C$1&"-"&$C86,rawdata!$E$3:$AC$14541,MATCH("ps_data",rawdata!$E$3:$AC$3,0),0), "") | K86: =IF(ISNUMBER(VLOOKUP($C$1&"-"&$C86,rawdata!$E$3:$AC$14541,MATCH("nfps_data",rawdata!$E$3:$AC$3,0),0)), VLOOKUP($C$1&"-"&$C86,rawdata!$E$3:$AC$14541,MATCH("nfps_data",rawdata!$E$3:$AC$3,0),0), "") | L86: =IF(ISNUMBER(VLOOKUP($C$1&"-"&$C86,rawdata!$E$3:$AC$14541,MATCH("gg_data",rawdata!$E$3:$AC$3,0),0)), VLOOKUP($C$1&"-"&$C86,rawdata!$E$3:$AC$14541,MATCH("gg_data",rawdata!$E$3:$AC$3,0),0), "") -> 81.285982 | M86: =IF(ISNUMBER(VLOOKUP($C$1&"-"&$C86,rawdata!$E$3:$AC$14541,MATCH("cg_data",rawdata!$E$3:$AC$3,0),0)), VLOOKUP($C$1&"-"&$C86,rawdata!$E$3:$AC$14541,MATCH("cg_data",rawdata!$E$3:$AC$3,0),0), "") -> 53.819233 | N86: =IF(ISNUMBER(VLOOKUP($C$1&"-"&$C86,rawdata!$E$3:$AC$14541,MATCH("ngdp_data",rawdata!$E$3:$AC$3,0),0)), VLOOKUP($C$1&"-"&$C86,rawdata!$E$3:$AC$14541,MATCH("ngdp_data",rawdata!$E$3:$AC$3,0),0), "") -> 330728.48

Sheet rawdata
F1: Data | Q1: Source
F2: Private | L2: Public | P2: Other | Q2: Private | Y2: Public | AC2: Other
A3: dept | B3: ifscode | C3: country | D3: year | E3: code | F3: tot_all_data | G3: hh_all_data | H3: nfc_all_data | I3: tot_ls_data | J3: hh_ls_data | K3: nfc_ls_data | L3: ps_data | M3: nfps_data | N3: gg_data | O3: cg_data | P3: ngdp_data | Q3: tot_all_source | R3: hh_all_source | S3: nfc_all_source | T3: dl_source | U3: cb_source | V3: sec_source | W3: hh_ls_source | X3: nfc_ls_source | Y3: ps_source | Z3: nfps_source | AA3: gg_source | AB3: cg_source | AC3: ngdp_source
A4: WHD | B4: 111 | C4: United States | D4: 1950 | E4: 111-1950 | F4: 75.826082 | G4: 25.482242 | H4: 50.343839 | I4: 55.314634 | J4: 24.802614 | K4: 30.51202 | N4: 83.126037 | O4: 78.199645 | P4: 301.7827 | Q4: OECD (1950-2024) | R4: OECD (1950-2024) | S4: OECD (1950-2024) | T4: National Source (1950-2024) | U4: National Source (1950-2024) | V4: National Source (1950-2024) | W4: National Source (1950-2024) | X4: National Source (1950-2024) | AA4: National Source (1950-2000); WEO 2025 (2001-2024) | AB4: National Source (1950-2000); IMF Staff (2001-2024) | AC4: WEO 2025 (1950-2024)
A5: WHD | B5: 111 | C5: United States | D5: 1951 | E5: 111-1951 | F5: 72.692564 | G5: 24.518253 | H5: 48.174311 | I5: 53.657228 | J5: 23.91165 | K5: 29.745577 | N5: 72.955032 | O5: 68.201929 | P5: 348.99306 | Q5: OECD (1950-2024) | R5: OECD (1950-2024) | S5: OECD (1950-2024) | T5: National Source (1950-2024) | U5: National Source (1950-2024) | V5: National Source (1950-2024) | W5: National Source (1950-2024) | X5: National Source (1950-2024) | AA5: National Source (1950-2000); WEO 2025 (2001-2024) | AB5: National Source (1950-2000); IMF Staff (2001-2024) | AC5: WEO 2025 (1950-2024)
A6: WHD | B6: 111 | C6: United States | D6: 1952 | E6: 111-1952 | F6: 88.242238 | G6: 26.598532 | H6: 61.643707 | I6: 56.555505 | J6: 25.976296 | K6: 30.579209 | N6: 72.525492 | O6: 66.341449 | P6: 368.02784 | Q6: OECD (1950-2024) | R6: OECD (1950-2024) | S6: OECD (1950-2024) | T6: National Source (1950-2024) | U6: National Source (1950-2024) | V6: National Source (1950-2024) | W6: National Source (1950-2024) | X6: National Source (1950-2024) | AA6: National Source (1950-2000); WEO 2025 (2001-2024) | AB6: National Source (1950-2000); IMF Staff (2001-2024) | AC6: WEO 2025 (1950-2024)
A7: WHD | B7: 111 | C7: United States | D7: 1953 | E7: 111-1953 | F7: 88.049345 | G7: 28.427253 | H7: 59.622092 | I7: 58.016532 | J7: 27.794074 | K7: 30.222458 | N7: 71.753219 | O7: 64.602206 | P7: 389.1477 | Q7: OECD (1950-2024) | R7: OECD (1950-2024) | S7: OECD (1950-2024) | T7: National Source (1950-2024) | U7: National Source (1950-2024) | V7: National Source (1950-2024) | W7: National Source (1950-2024) | X7: National Source (1950-2024) | AA7: National Source (1950-2000); WEO 2025 (2001-2024) | AB7: National Source (1950-2000); IMF Staff (2001-2024) | AC7: WEO 2025 (1950-2024)
A8: WHD | B8: 111 | C8: United States | D8: 1954 | E8: 111-1954 | F8: 106.05707 | G8: 31.539677 | H8: 74.517393 | I8: 62.573558 | J8: 30.862721 | K8: 31.710837 | N8: 73.568066 | O8: 64.955715 | P8: 390.27667 | Q8: OECD (1950-2024) | R8: OECD (1950-2024) | S8: OECD (1950-2024) | T8: National Source (1950-2024) | U8: National Source (1950-2024) | V8: National Source (1950-2024) | W8: National Source (1950-2024) | X8: National Source (1950-2024) | AA8: National Source (1950-2000); WEO 2025 (2001-2024) | AB8: National Source (1950-2000); IMF Staff (2001-2024) | AC8: WEO 2025 (1950-2024)
A9: WHD | B9: 111 | C9: United States | D9: 1955 | E9: 111-1955 | F9: 120.12192 | G9: 33.99312 | H9: 86.128801 | I9: 65.340243 | J9: 33.318558 | K9: 32.021685 | N9: 68.498633 | O9: 59.520558 | P9: 424.86833 | Q9: OECD (1950-2024) | R9: OECD (1950-2024) | S9: OECD (1950-2024) | T9: National Source (1950-2024) | U9: National Source (1950-2024) | V9: National Source (1950-2024) | W9: National Source (1950-2024) | X9: National Source (1950-2024) | AA9: National Source (1950-2000); WEO 2025 (2001-2024) | AB9: National Source (1950-2000); IMF Staff (2001-2024) | AC9: WEO 2025 (1950-2024)
A10: WHD | B10: 111 | C10: United States | D10: 1956 | E10: 111-1956 | F10: 126.1808 | G10: 35.593922 | H10: 90.586875 | I10: 68.086068 | J10: 34.880478 | K10: 33.20559 | N10: 64.726033 | O10: 55.370304 | P10: 448.38836 | Q10: OECD (1950-2024) | R10: OECD (1950-2024) | S10: OECD (1950-2024) | T10: National Source (1950-2024) | U10: National Source (1950-2024) | V10: National Source (1950-2024) | W10: National Source (1950-2024) | X10: National Source (1950-2024) | AA10: National Source (1950-2000); WEO 2025 (2001-2024) | AB10: National Source (1950-2000); IMF Staff (2001-2024) | AC10: WEO 2025 (1950-2024)
A11: WHD | B11: 111 | C11: United States | D11: 1957 | E11: 111-1957 | F11: 120.82048 | G11: 36.479192 | H11: 84.34129 | I11: 69.869603 | J11: 35.736146 | K11: 34.133457 | N11: 62.329546 | O11: 52.249566 | P11: 471.70727 | Q11: OECD (1950-2024) | R11: OECD (1950-2024) | S11: OECD (1950-2024) | T11: National Source (1950-2024) | U11: National Source (1950-2024) | V11: National Source (1950-2024) | W11: National Source (1950-2024) | X11: National Source (1950-2024) | AA11: National Source (1950-2000); WEO 2025 (2001-2024) | AB11: National Source (1950-2000); IMF Staff (2001-2024) | AC11: WEO 2025 (1950-2024)
A12: WHD | B12: 111 | C12: United States | D12: 1958 | E12: 111-1958 | F12: 140.79792 | G12: 38.510823 | H12: 102.28709 | I12: 73.723216 | J12: 37.72114 | K12: 36.002075 | N12: 64.927332 | O12: 53.659927 | P12: 478.16688 | Q12: OECD (1950-2024) | R12: OECD (1950-2024) | S12: OECD (1950-2024) | T12: National Source (1950-2024) | U12: National Source (1950-2024) | V12: National Source (1950-2024) | W12: National Source (1950-2024) | X12: National Source (1950-2024) | AA12: National Source (1950-2000); WEO 2025 (2001-2024) | AB12: National Source (1950-2000); IMF Staff (2001-2024) | AC12: WEO 2025 (1950-2024)
A13: WHD | B13: 111 | C13: United States | D13: 1959 | E13: 111-1959 | F13: 145.40939 | G13: 39.789706 | H13: 105.61969 | I13: 74.923568 | J13: 38.945009 | K13: 35.978559 | N13: 62.335885 | O13: 50.901287 | P13: 519.47606 | Q13: OECD (1950-2024) | R13: OECD (1950-2024) | S13: OECD (1950-2024) | T13: National Source (1950-2024) | U13: National Source (1950-2024) | V13: National Source (1950-2024) | W13: National Source (1950-2024) | X13: National Source (1950-2024) | AA13: National Source (1950-2000); WEO 2025 (2001-2024) | AB13: National Source (1950-2000); IMF Staff (2001-2024) | AC13: WEO 2025 (1950-2024)
A14: WHD | B14: 111 | C14: United States | D14: 1960 | E14: 111-1960 | F14: 146.60089 | G14: 41.59012 | H14: 105.01077 | I14: 77.881108 | J14: 40.722366 | K14: 37.158742 | N14: 60.832947 | O14: 48.843131 | P14: 539.89987 | Q14: OECD (1950-2024) | R14: OECD (1950-2024) | S14: OECD (1950-2024) | T14: National Source (1950-2024) | U14: National Source (1950-2024) | V14: National Source (1950-2024) | W14: National Source (1950-2024) | X14: National Source (1950-2024) | AA14: National Source (1950-2000); WEO 2025 (2001-2024) | AB14: National Source (1950-2000); IMF Staff (2001-2024) | AC14: WEO 2025 (1950-2024)
A15: WHD | B15: 111 | C15: United States | D15: 1961 | E15: 111-1961 | F15: 160.18041 | G15: 43.486442 | H15: 116.69397 | I15: 81.028202 | J15: 42.589888 | K15: 38.438314 | N15: 61.393351 | O15: 48.71073 | P15: 558.58329 | Q15: OECD (1950-2024) | R15: OECD (1950-2024) | S15: OECD (1950-2024) | T15: National Source (1950-2024) | U15: National Source (1950-2024) | V15: National Source (1950-2024) | W15: National Source (1950-2024) | X15: National Source (1950-2024) | AA15: National Source (1950-2000); WEO 2025 (2001-2024) | AB15: National Source (1950-2000); IMF Staff (2001-2024) | AC15: WEO 2025 (1950-2024)
... A78: WHD | B78: 111 | C78: United States | D78: 2024 | E78: 111-2024 | F78: 216.62001 | G78: 71.399727 | H78: 145.22029 | I78: 143.12024 | J78: 69.353741 | K78: 73.766503 | N78: 120.78568 | O78: 102.68658 | P78: 29184.9 | Q78: OECD (1950-2024) | R78: OECD (1950-2024) | S78: OECD (1950-2024) | T78: National Source (1950-2024) | U78: National Source (1950-2024) | V78: National Source (1950-2024) | W78: National Source (1950-2024) | X78: National Source (1950-2024) | AA78: National Source (1950-2000); WEO 2025 (2001-2024) | AB78: National Source (1950-2000); IMF Staff (2001-2024) | AC78: WEO 2025 (1950-2024)
A79: EUR | B79: 112 | C79: United Kingdom | D79: 1950 | E79: 112-1950 | N79: 179.89667 | P79: 14.342678 | Q79: OECD (1995-2024) | R79: OECD (1995-2024) | S79: OECD (1995-2024) | T79: BIS (1963-2024) | U79: BIS (1963-2024) | V79: BIS (1963-2024) | W79: BIS (1966-2024) | X79: BIS (1966-2024) | Y79: National Source (1974-2024) | AA79: National Source (1950-1966); WEO 2002 (1967-1973); National Source (1974-2024) | AB79: National Source (1974-2024) | AC79: WEO 2025 (1950-2024)
A80: EUR | B80: 112 | C80: United Kingdom | D80: 1951 | E80: 112-1951 | N80: 162.18009 | P80: 15.983466 | Q80: OECD (1995-2024) | R80: OECD (1995-2024) | S80: OECD (1995-2024) | T80: BIS (1963-2024) | U80: BIS (1963-2024) | V80: BIS (1963-2024) | W80: BIS (1966-2024) | X80: BIS (1966-2024) | Y80: National Source (1974-2024) | AA80: National Source (1950-1966); WEO 2002 (1967-1973); National Source (1974-2024) | AB80: National Source (1974-2024) | AC80: WEO 2025 (1950-2024)
A81: EUR | B81: 112 | C81: United Kingdom | D81: 1952 | E81: 112-1952 | N81: 150.14853 | P81: 17.243592 | Q81: OECD (1995-2024) | R81: OECD (1995-2024) | S81: OECD (1995-2024) | T81: BIS (1963-2024) | U81: BIS (1963-2024) | V81: BIS (1963-2024) | W81: BIS (1966-2024) | X81: BIS (1966-2024) | Y81: National Source (1974-2024) | AA81: National Source (1950-1966); WEO 2002 (1967-1973); National Source (1974-2024) | AB81: National Source (1974-2024) | AC81: WEO 2025 (1950-2024)
A82: EUR | B82: 112 | C82: United Kingdom | D82: 1953 | E82: 112-1953 | N82: 140.87122 | P82: 18.492777 | Q82: OECD (1995-2024) | R82: OECD (1995-2024) | S82: OECD (1995-2024) | T82: BIS (1963-2024) | U82: BIS (1963-2024) | V82: BIS (1963-2024) | W82: BIS (1966-2024) | X82: BIS (1966-2024) | Y82: National Source (1974-2024) | AA82: National Source (1950-1966); WEO 2002 (1967-1973); National Source (1974-2024) | AB82: National Source (1974-2024) | AC82: WEO 2025 (1950-2024)
A83: EUR | B83: 112 | C83: United Kingdom | D83: 1954 | E83: 112-1954 | N83: 135.84146 | P83: 19.569136 | Q83: OECD (1995-2024) | R83: OECD (1995-2024) | S83: OECD (1995-2024) | T83: BIS (1963-2024) | U83: BIS (1963-2024) | V83: BIS (1963-2024) | W83: BIS (1966-2024) | X83: BIS (1966-2024) | Y83: National Source (1974-2024) | AA83: National Source (1950-1966); WEO 2002 (1967-1973); National Source (1974-2024) | AB83: National Source (1974-2024) | AC83: WEO 2025 (1950-2024)
A84: EUR | B84: 112 | C84: United Kingdom | D84: 1955 | E84: 112-1955 | N84: 127.55345 | P84: 21.115854 | Q84: OECD (1995-2024) | R84: OECD (1995-2024) | S84: OECD (1995-2024) | T84: BIS (1963-2024) | U84: BIS (1963-2024) | V84: BIS (1963-2024) | W84: BIS (1966-2024) | X84: BIS (1966-2024) | Y84: National Source (1974-2024) | AA84: National Source (1950-1966); WEO 2002 (1967-1973); National Source (1974-2024) | AB84: National Source (1974-2024) | AC84: WEO 2025 (1950-2024)
A85: EUR | B85: 112 | C85: United Kingdom | D85: 1956 | E85: 112-1956 | N85: 119.0355 | P85: 22.715073 | Q85: OECD (1995-2024) | R85: OECD (1995-2024) | S85: OECD (1995-2024) | T85: BIS (1963-2024) | U85: BIS (1963-2024) | V85: BIS (1963-2024) | W85: BIS (1966-2024) | X85: BIS (1966-2024) | Y85: National Source (1974-2024) | AA85: National Source (1950-1966); WEO 2002 (1967-1973); National Source (1974-2024) | AB85: National Source (1974-2024) | AC85: WEO 2025 (1950-2024)
A86: EUR | B86: 112 | C86: United Kingdom | D86: 1957 | E86: 112-1957 | N86: 112.63947 | P86: 23.977386 | Q86: OECD (1995-2024) | R86: OECD (1995-2024) | S86: OECD (1995-2024) | T86: BIS (1963-2024) | U86: BIS (1963-2024) | V86: BIS (1963-2024) | W86: BIS (1966-2024) | X86: BIS (1966-2024) | Y86: National Source (1974-2024) | AA86: National Source (1950-1966); WEO 2002 (1967-1973); National Source (1974-2024) | AB86: National Source (1974-2024) | AC86: WEO 2025 (1950-2024)
A87: EUR | B87: 112 | C87: United Kingdom | D87: 1958 | E87: 112-1958 | N87: 108.93689 | P87: 24.997959 | Q87: OECD (1995-2024) | R87: OECD (1995-2024) | S87: OECD (1995-2024) | T87: BIS (1963-2024) | U87: BIS (1963-2024) | V87: BIS (1963-2024) | W87: BIS (1966-2024) | X87: BIS (1966-2024) | Y87: National Source (1974-2024) | AA87: National Source (1950-1966); WEO 2002 (1967-1973); National Source (1974-2024) | AB87: National Source (1974-2024) | AC87: WEO 2025 (1950-2024)
A88: EUR | B88: 112 | C88: United Kingdom | D88: 1959 | E88: 112-1959 | N88: 103.3618 | P88: 26.485608 | Q88: OECD (1995-2024) | R88: OECD (1995-2024) | S88: OECD (1995-2024) | T88: BIS (1963-2024) | U88: BIS (1963-2024) | V88: BIS (1963-2024) | W88: BIS (1966-2024) | X88: BIS (1966-2024) | Y88: National Source (1974-2024) | AA88: National Source (1950-1966); WEO 2002 (1967-1973); National Source (1974-2024) | AB88: National Source (1974-2024) | AC88: WEO 2025 (1950-2024)
A89: EUR | B89: 112 | C89: United Kingdom | D89: 1960 | E89: 112-1960 | N89: 97.938579 | P89: 28.316727 | Q89: OECD (1995-2024) | R89: OECD (1995-2024) | S89: OECD (1995-2024) | T89: BIS (1963-2024) | U89: BIS (1963-2024) | V89: BIS (1963-2024) | W89: BIS (1966-2024) | X89: BIS (1966-2024) | Y89: National Source (1974-2024) | AA89: National Source (1950-1966); WEO 2002 (1967-1973); National Source (1974-2024) | AB89: National Source (1974-2024) | AC89: WEO 2025 (1950-2024)
A90: EUR | B90: 112 | C90: United Kingdom | D90: 1961 | E90: 112-1961 | N90: 94.152184 | P90: 30.006739 | Q90: OECD (1995-2024) | R90: OECD (1995-2024) | S90: OECD (1995-2024) | T90: BIS (1963-2024) | U90: BIS (1963-2024) | V90: BIS (1963-2024) | W90: BIS (1966-2024) | X90: BIS (1966-2024) | Y90: National Source (1974-2024) | AA90: National Source (1950-1966); WEO 2002 (1967-1973); National Source (1974-2024) | AB90: National Source (1974-2024) | AC90: WEO 2025 (1950-2024)
A91: EUR | B91: 112 | C91: United Kingdom | D91: 1962 | E91: 112-1962 | N91: 90.98159 | P91: 31.516266 | Q91: OECD (1995-2024) | R91: OECD (1995-2024) | S91: OECD (1995-2024) | T91: BIS (1963-2024) | U91: BIS (1963-2024) | V91: BIS (1963-2024) | W91: BIS (1966-2024) | X91: BIS (1966-2024) | Y91: National Source (1974-2024) | AA91: National Source (1950-1966); WEO 2002 (1967-1973); National Source (1974-2024) | AB91: National Source (1974-2024) | AC91: WEO 2025 (1950-2024)
A92: EUR | B92: 112 | C92: United Kingdom | D92: 1963 | E92: 112-1963 | I92: 48.92582 | N92: 89.213628 | P92: 33.456772 | Q92: OECD (1995-2024) | R92: OECD (1995-2024) | S92: OECD (1995-2024) | T92: BIS (1963-2024) | U92: BIS (1963-2024) | V92: BIS (1963-2024) | W92: BIS (1966-2024) | X92: BIS (1966-2024) | Y92: National Source (1974-2024) | AA92: National Source (1950-1966); WEO 2002 (1967-1973); National Source (1974-2024) | AB92: National Source (1974-2024) | AC92: WEO 2025 (1950-2024)
A93: EUR | B93: 112 | C93: United Kingdom | D93: 1964 | E93: 112-1964 | I93: 52.215866 | N93: 82.645272 | P93: 36.573175 | Q93: OECD (1995-2024) | R93: OECD (1995-2024) | S93: OECD (1995-2024) | T93: BIS (1963-2024) | U93: BIS (1963-2024) | V93: BIS (1963-2024) | W93: BIS (1966-2024) | X93: BIS (1966-2024) | Y93: National Source (1974-2024) | AA93: National Source (1950-1966); WEO 2002 (1967-1973); National Source (1974-2024) | AB93: National Source (1974-2024) | AC93: WEO 2025 (1950-2024)
A94: EUR | B94: 112 | C94: United Kingdom | D94: 1965 | E94: 112-1965 | I94: 55.371758 | N94: 77.227696 | P94: 39.417206 | Q94: OECD (1995-2024) | R94: OECD (1995-2024) | S94: OECD (1995-2024) | T94: BIS (1963-2024) | U94: BIS (1963-2024) | V94: BIS (1963-2024) | W94: BIS (1966-2024) | X94: BIS (1966-2024) | Y94: National Source (1974-2024) | AA94: National Source (1950-1966); WEO 2002 (1967-1973); National Source (1974-2024) | AB94: National Source (1974-2024) | AC94: WEO 2025 (1950-2024)
A95: EUR | B95: 112 | C95: United Kingdom | D95: 1966 | E95: 112-1966 | I95: 58.501783 | J95: 30.844835 | K95: 27.656948 | N95: 74.67233 | P95: 41.97137 | Q95: OECD (1995-2024) | R95: OECD (1995-2024) | S95: OECD (1995-2024) | T95: BIS (1963-2024) | U95: BIS (1963-2024) | V95: BIS (1963-2024) | W95: BIS (1966-2024) | X95: BIS (1966-2024) | Y95: National Source (1974-2024) | AA95: National Source (1950-1966); WEO 2002 (1967-1973); National Source (1974-2024) | AB95: National Source (1974-2024) | AC95: WEO 2025 (1950-2024)
A96: EUR | B96: 112 | C96: United Kingdom | D96: 1967 | E96: 112-1967 | I96: 59.266514 | J96: 31.250069 | K96: 28.016445 | N96: 71.868372 | P96: 44.191902 | Q96: OECD (1995-2024) | R96: OECD (1995-2024) | S96: OECD (1995-2024) | T96: BIS (1963-2024) | U96: BIS (1963-2024) | V96: BIS (1963-2024) | W96: BIS (1966-2024) | X96: BIS (1966-2024) | Y96: National Source (1974-2024) | AA96: National Source (1950-1966); WEO 2002 (1967-1973); National Source (1974-2024) | AB96: National Source (1974-2024) | AC96: WEO 2025 (1950-2024)
A97: EUR | B97: 112 | C97: United Kingdom | D97: 1968 | E97: 112-1968 | I97: 58.07206 | J97: 30.619927 | K97: 27.452133 | N97: 70.964438 | P97: 47.919775 | Q97: OECD (1995-2024) | R97: OECD (1995-2024) | S97: OECD (1995-2024) | T97: BIS (1963-2024) | U97: BIS (1963-2024) | V97: BIS (1963-2024) | W97: BIS (1966-2024) | X97: BIS (1966-2024) | Y97: National Source (1974-2024) | AA97: National Source (1950-1966); WEO 2002 (1967-1973); National Source (1974-2024) | AB97: National Source (1974-2024) | AC97: WEO 2025 (1950-2024)
A98: EUR | B98: 112 | C98: United Kingdom | D98: 1969 | E98: 112-1969 | I98: 57.126257 | J98: 30.120941 | K98: 27.005316 | N98: 66.036904 | P98: 51.578734 | Q98: OECD (1995-2024) | R98: OECD (1995-2024) | S98: OECD (1995-2024) | T98: BIS (1963-2024) | U98: BIS (1963-2024) | V98: BIS (1963-2024) | W98: BIS (1966-2024) | X98: BIS (1966-2024) | Y98: National Source (1974-2024) | AA98: National Source (1950-1966); WEO 2002 (1967-1973); National Source (1974-2024) | AB98: National Source (1974-2024) | AC98: WEO 2025 (1950-2024)
A99: EUR | B99: 112 | C99: United Kingdom | D99: 1970 | E99: 112-1970 | I99: 57.811286 | J99: 30.482571 | K99: 27.328715 | N99: 73.421641 | P99: 56.629081 | Q99: OECD (1995-2024) | R99: OECD (1995-2024) | S99: OECD (1995-2024) | T99: BIS (1963-2024) | U99: BIS (1963-2024) | V99: BIS (1963-2024) | W99: BIS (1966-2024) | X99: BIS (1966-2024) | Y99: National Source (1974-2024) | AA99: National Source (1950-1966); WEO 2002 (1967-1973); National Source (1974-2024) | AB99: National Source (1974-2024) | AC99: WEO 2025 (1950-2024)
A100: EUR | B100: 112 | C100: United Kingdom | D100: 1971 | E100: 112-1971 | I100: 57.009728 | J100: 30.059445 | K100: 26.950284 | N100: 67.936117 | P100: 63.168166 | Q100: OECD (1995-2024) | R100: OECD (1995-2024) | S100: OECD (1995-2024) | T100: BIS (1963-2024) | U100: BIS (1963-2024) | V100: BIS (1963-2024) | W100: BIS (1966-2024) | X100: BIS (1966-2024) | Y100: National Source (1974-2024) | AA100: National Source (1950-1966); WEO 2002 (1967-1973); National Source (1974-2024) | AB100: National Source (1974-2024) | AC100: WEO 2025 (1950-2024)
A101: EUR | B101: 112 | C101: United Kingdom | D101: 1972 | E101: 112-1972 | I101: 64.79934 | J101: 34.166899 | K101: 30.632441 | N101: 65.039682 | P101: 70.732202 | Q101: OECD (1995-2024) | R101: OECD (1995-2024) | S101: OECD (1995-2024) | T101: BIS (1963-2024) | U101: BIS (1963-2024) | V101: BIS (1963-2024) | W101: BIS (1966-2024) | X101: BIS (1966-2024) | Y101: National Source (1974-2024) | AA101: National Source (1950-1966); WEO 2002 (1967-1973); National Source (1974-2024) | AB101: National Source (1974-2024) | AC101: WEO 2025 (1950-2024)
A102: EUR | B102: 112 | C102: United Kingdom | D102: 1973 | E102: 112-1973 | I102: 64.488658 | J102: 34.002372 | K102: 30.486286 | N102: 58.538645 | P102: 81.226686 | Q102: OECD (1995-2024) | R102: OECD (1995-2024) | S102: OECD (1995-2024) | T102: BIS (1963-2024) | U102: BIS (1963-2024) | V102: BIS (1963-2024) | W102: BIS (1966-2024) | X102: BIS (1966-2024) | Y102: National Source (1974-2024) | AA102: National Source (1950-1966); WEO 2002 (1967-1973); National Source (1974-2024) | AB102: National Source (1974-2024) | AC102: WEO 2025 (1950-2024)
A103: EUR | B103: 112 | C103: United Kingdom | D103: 1974 | E103: 112-1974 | I103: 62.455029 | J103: 32.930279 | K103: 29.524751 | L103: 61.024795 | N103: 56.166139 | O103: 37.75187 | P103: 91.733205 | Q103: OECD (1995-2024) | R103: OECD (1995-2024) | S103: OECD (1995-2024) | T103: BIS (1963-2024) | U103: BIS (1963-2024) | V103: BIS (1963-2024) | W103: BIS (1966-2024) | X103: BIS (1966-2024) | Y103: National Source (1974-2024) | AA103: National Source (1950-1966); WEO 2002 (1967-1973); National Source (1974-2024) | AB103: National Source (1974-2024) | AC103: WEO 2025 (1950-2024)
A104: EUR | B104: 112 | C104: United Kingdom | D104: 1975 | E104: 112-1975 | I104: 57.95933 | J104: 30.560044 | K104: 27.399286 | L104: 59.680475 | N104: 49.589365 | O104: 37.285724 | P104: 115.79499 | Q104: OECD (1995-2024) | R104: OECD (1995-2024) | S104: OECD (1995-2024) | T104: BIS (1963-2024) | U104: BIS (1963-2024) | V104: BIS (1963-2024) | W104: BIS (1966-2024) | X104: BIS (1966-2024) | Y104: National Source (1974-2024) | AA104: National Source (1950-1966); WEO 2002 (1967-1973); National Source (1974-2024) | AB104: National Source (1974-2024) | AC104: WEO 2025 (1950-2024)
A105: EUR | B105: 112 | C105: United Kingdom | D105: 1976 | E105: 112-1976 | I105: 58.907477 | J105: 30.21403 | K105: 28.693447 | L105: 59.231283 | N105: 47.683601 | O105: 36.273755 | P105: 137.11842 | Q105: OECD (1995-2024) | R105: OECD (1995-2024) | S105: OECD (1995-2024) | T105: BIS (1963-2024) | U105: BIS (1963-2024) | V105: BIS (1963-2024) | W105: BIS (1966-2024) | X105: BIS (1966-2024) | Y105: National Source (1974-2024) | AA105: National Source (1950-1966); WEO 2002 (1967-1973); National Source (1974-2024) | AB105: National Source (1974-2024) | AC105: WEO 2025 (1950-2024)
A106: EUR | B106: 112 | C106: United Kingdom | D106: 1977 | E106: 112-1977 | I106: 56.345654 | J106: 29.717881 | K106: 26.627772 | L106: 57.694133 | N106: 53.680622 | O106: 44.860415 | P106: 159.73548 | Q106: OECD (1995-2024) | R106: OECD (1995-2024) | S106: OECD (1995-2024) | T106: BIS (1963-2024) | U106: BIS (1963-2024) | V106: BIS (1963-2024) | W106: BIS (1966-2024) | X106: BIS (1966-2024) | Y106: National Source (1974-2024) | AA106: National Source (1950-1966); WEO 2002 (1967-1973); National Source (1974-2024) | AB106: National Source (1974-2024) | AC106: WEO 2025 (1950-2024)
A107: EUR | B107: 112 | C107: United Kingdom | D107: 1978 | E107: 112-1978 | I107: 55.795157 | J107: 30.140914 | K107: 25.654243 | L107: 54.782955 | N107: 47.254308 | O107: 39.072888 | P107: 186.12906 | Q107: OECD (1995-2024) | R107: OECD (1995-2024) | S107: OECD (1995-2024) | T107: BIS (1963-2024) | U107: BIS (1963-2024) | V107: BIS (1963-2024) | W107: BIS (1966-2024) | X107: BIS (1966-2024) | Y107: National Source (1974-2024) | AA107: National Source (1950-1966); WEO 2002 (1967-1973); National Source (1974-2024) | AB107: National Source (1974-2024) | AC107: WEO 2025 (1950-2024)
A108: EUR | B108: 112 | C108: United Kingdom | D108: 1979 | E108: 112-1979 | I108: 55.872224 | J108: 30.855594 | K108: 25.01663 | L108: 50.748254 | N108: 44.521022 | O108: 38.455795 | P108: 220.981 | Q108: OECD (1995-2024) | R108: OECD (1995-2024) | S108: OECD (1995-2024) | T108: BIS (1963-2024) | U108: BIS (1963-2024) | V108: BIS (1963-2024) | W108: BIS (1966-2024) | X108: BIS (1966-2024) | Y108: National Source (1974-2024) | AA108: National Source (1950-1966); WEO 2002 (1967-1973); National Source (1974-2024) | AB108: National Source (1974-2024) | AC108: WEO 2025 (1950-2024)
A109: EUR | B109: 112 | C109: United Kingdom | D109: 1980 | E109: 112-1980 | I109: 56.813863 | J109: 30.211948 | K109: 26.601916 | L109: 50.021156 | N109: 43.709274 | O109: 36.77809 | P109: 259.97 | Q109: OECD (1995-2024) | R109: OECD (1995-2024) | S109: OECD (1995-2024) | T109: BIS (1963-2024) | U109: BIS (1963-2024) | V109: BIS (1963-2024) | W109: BIS (1966-2024) | X109: BIS (1966-2024) | Y109: National Source (1974-2024) | AA109: National Source (1950-1966); WEO 2002 (1967-1973); National Source (1974-2024) | AB109: National Source (1974-2024) | AC109: WEO 2025 (1950-2024)
A110: EUR | B110: 112 | C110: United Kingdom | D110: 1981 | E110: 112-1981 | I110: 60.840168 | J110: 31.825419 | K110: 29.014749 | L110: 47.638018 | N110: 41.131367 | O110: 33.421325 | P110: 290.18 | Q110: OECD (1995-2024) | R110: OECD (1995-2024) | S110: OECD (1995-2024) | T110: BIS (1963-2024) | U110: BIS (1963-2024) | V110: BIS (1963-2024) | W110: BIS (1966-2024) | X110: BIS (1966-2024) | Y110: National Source (1974-2024) | AA110: National Source (1950-1966); WEO 2002 (1967-1973); National Source (1974-2024) | AB110: National Source (1974-2024) | AC110: WEO 2025 (1950-2024)
A111: EUR | B111: 112 | C111: United Kingdom | D111: 1982 | E111: 112-1982 | I111: 65.568692 | J111: 34.571502 | K111: 30.99719 | L111: 46.086782 | N111: 44.700805 | O111: 37.7922 | P111: 319.558 | Q111: OECD (1995-2024) | R111: OECD (1995-2024) | S111: OECD (1995-2024) | T111: BIS (1963-2024) | U111: BIS (1963-2024) | V111: BIS (1963-2024) | W111: BIS (1966-2024) | X111: BIS (1966-2024) | Y111: National Source (1974-2024) | AA111: National Source (1950-1966); WEO 2002 (1967-1973); National Source (1974-2024) | AB111: National Source (1974-2024) | AC111: WEO 2025 (1950-2024)
A112: EUR | B112: 112 | C112: United Kingdom | D112: 1983 | E112: 112-1983 | I112: 68.428078 | J112: 37.093529 | K112: 31.33455 | L112: 45.346054 | N112: 44.199324 | O112: 39.338887 | P112: 351.347 | Q112: OECD (1995-2024) | R112: OECD (1995-2024) | S112: OECD (1995-2024) | T112: BIS (1963-2024) | U112: BIS (1963-2024) | V112: BIS (1963-2024) | W112: BIS (1966-2024) | X112: BIS (1966-2024) | Y112: National Source (1974-2024) | AA112: National Source (1950-1966); WEO 2002 (1967-1973); National Source (1974-2024) | AB112: National Source (1974-2024) | AC112: WEO 2025 (1950-2024)
A113: EUR | B113: 112 | C113: United Kingdom | D113: 1984 | E113: 112-1984 | I113: 75.966607 | J113: 41.108436 | K113: 34.858171 | L113: 45.454329 | N113: 44.139236 | O113: 39.729837 | P113: 377.92 | Q113: OECD (1995-2024) | R113: OECD (1995-2024) | S113: OECD (1995-2024) | T113: BIS (1963-2024) | U113: BIS (1963-2024) | V113: BIS (1963-2024) | W113: BIS (1966-2024) | X113: BIS (1966-2024) | Y113: National Source (1974-2024) | AA113: National Source (1950-1966); WEO 2002 (1967-1973); National Source (1974-2024) | AB113: National Source (1974-2024) | AC113: WEO 2025 (1950-2024)
A114: EUR | B114: 112 | C114: United Kingdom | D114: 1985 | E114: 112-1985 | I114: 77.346309 | J114: 42.464848 | K114: 34.881461 | L114: 44.044087 | N114: 42.894147 | O114: 40.227432 | P114: 414.63 | Q114: OECD (1995-2024) | R114: OECD (1995-2024) | S114: OECD (1995-2024) | T114: BIS (1963-2024) | U114: BIS (1963-2024) | V114: BIS (1963-2024) | W114: BIS (1966-2024) | X114: BIS (1966-2024) | Y114: National Source (1974-2024) | AA114: National Source (1950-1966); WEO 2002 (1967-1973); National Source (1974-2024) | AB114: National Source (1974-2024) | AC114: WEO 2025 (1950-2024)
... A123: EUR | B123: 112 | C123: United Kingdom | D123: 1994 | E123: 112-1994 | I123: 110.86404 | J123: 58.282622 | K123: 52.58142 | L123: 41.401022 | N123: 40.703311 | O123: 39.447011 | P123: 810.794 | Q123: OECD (1995-2024) | R123: OECD (1995-2024) | S123: OECD (1995-2024) | T123: BIS (1963-2024) | U123: BIS (1963-2024) | V123: BIS (1963-2024) | W123: BIS (1966-2024) | X123: BIS (1966-2024) | Y123: National Source (1974-2024) | AA123: National Source (1950-1966); WEO 2002 (1967-1973); National Source (1974-2024) | AB123: National Source (1974-2024) | AC123: WEO 2025 (1950-2024)
A124: EUR | B124: 112 | C124: United Kingdom | D124: 1995 | E124: 112-1995 | F124: 155.5722 | G124: 65.497244 | H124: 90.074955 | I124: 111.99127 | J124: 58.121137 | K124: 53.870129 | L124: 43.61486 | N124: 45.057845 | O124: 42.43495 | P124: 851.845 | Q124: OECD (1995-2024) | R124: OECD (1995-2024) | S124: OECD (1995-2024) | T124: BIS (1963-2024) | U124: BIS (1963-2024) | V124: BIS (1963-2024) | W124: BIS (1966-2024) | X124: BIS (1966-2024) | Y124: National Source (1974-2024) | AA124: National Source (1950-1966); WEO 2002 (1967-1973); National Source (1974-2024) | AB124: National Source (1974-2024) | AC124: WEO 2025 (1950-2024)
A125: EUR | B125: 112 | C125: United Kingdom | D125: 1996 | E125: 112-1996 | F125: 149.76489 | G125: 63.772029 | H125: 85.992859 | I125: 108.69974 | J125: 56.800437 | K125: 51.8993 | L125: 44.256384 | N125: 44.738476 | O125: 42.620218 | P125: 909.993 | Q125: OECD (1995-2024) | R125: OECD (1995-2024) | S125: OECD (1995-2024) | T125: BIS (1963-2024) | U125: BIS (1963-2024) | V125: BIS (1963-2024) | W125: BIS (1966-2024) | X125: BIS (1966-2024) | Y125: National Source (1974-2024) | AA125: National Source (1950-1966); WEO 2002 (1967-1973); National Source (1974-2024) | AB125: National Source (1974-2024) | AC125: WEO 2025 (1950-2024)
A126: EUR | B126: 112 | C126: United Kingdom | D126: 1997 | E126: 112-1997 | F126: 153.91151 | G126: 64.710905 | H126: 89.200602 | I126: 112.02826 | J126: 57.678846 | K126: 54.349411 | L126: 42.921109 | N126: 44.132032 | O126: 42.34811 | P126: 953.405 | Q126: OECD (1995-2024) | R126: OECD (1995-2024) | S126: OECD (1995-2024) | T126: BIS (1963-2024) | U126: BIS (1963-2024) | V126: BIS (1963-2024) | W126: BIS (1966-2024) | X126: BIS (1966-2024) | Y126: National Source (1974-2024) | AA126: National Source (1950-1966); WEO 2002 (1967-1973); National Source (1974-2024) | AB126: National Source (1974-2024) | AC126: WEO 2025 (1950-2024)
A127: EUR | B127: 112 | C127: United Kingdom | D127: 1998 | E127: 112-1998 | F127: 173.72091 | G127: 67.129427 | H127: 106.59148 | I127: 120.02742 | J127: 59.812158 | K127: 60.215263 | L127: 41.079779 | N127: 41.969512 | O127: 40.27357 | P127: 998.501 | Q127: OECD (1995-2024) | R127: OECD (1995-2024) | S127: OECD (1995-2024) | T127: BIS (1963-2024) | U127: BIS (1963-2024) | V127: BIS (1963-2024) | W127: BIS (1966-2024) | X127: BIS (1966-2024) | Y127: National Source (1974-2024) | AA127: National Source (1950-1966); WEO 2002 (1967-1973); National Source (1974-2024) | AB127: National Source (1974-2024) | AC127: WEO 2025 (1950-2024)
A128: EUR | B128: 112 | C128: United Kingdom | D128: 1999 | E128: 112-1999 | F128: 166.4448 | G128: 69.787337 | H128: 96.657458 | I128: 128.71436 | J128: 63.115482 | K128: 65.59888 | L128: 39.498278 | N128: 40.409759 | O128: 38.925931 | P128: 1043.248 | Q128: OECD (1995-2024) | R128: OECD (1995-2024) | S128: OECD (1995-2024) | T128: BIS (1963-2024) | U128: BIS (1963-2024) | V128: BIS (1963-2024) | W128: BIS (1966-2024) | X128: BIS (1966-2024) | Y128: National Source (1974-2024) | AA128: National Source (1950-1966); WEO 2002 (1967-1973); National Source (1974-2024) | AB128: National Source (1974-2024) | AC128: WEO 2025 (1950-2024)
A129: EUR | B129: 112 | C129: United Kingdom | D129: 2000 | E129: 112-2000 | F129: 183.52999 | G129: 71.999142 | H129: 111.53084 | I129: 136.01111 | J129: 65.27047 | K129: 70.740639 | L129: 36.952193 | N129: 37.685691 | O129: 37.331842 | P129: 1100.752 | Q129: OECD (1995-2024) | R129: OECD (1995-2024) | S129: OECD (1995-2024) | T129: BIS (1963-2024) | U129: BIS (1963-2024) | V129: BIS (1963-2024) | W129: BIS (1966-2024) | X129: BIS (1966-2024) | Y129: National Source (1974-2024) | AA129: National Source (1950-1966); WEO 2002 (1967-1973); National Source (1974-2024) | AB129: National Source (1974-2024) | AC129: WEO 2025 (1950-2024)
A130: EUR | B130: 112 | C130: United Kingdom | D130: 2001 | E130: 112-2001 | F130: 194.79032 | G130: 76.558695 | H130: 118.23162 | I130: 144.38613 | J130: 69.212353 | K130: 75.17378 | L130: 34.39176 | N130: 34.957749 | O130: 34.614509 | P130: 1146.135 | Q130: OECD (1995-2024) | R130: OECD (1995-2024) | S130: OECD (1995-2024) | T130: BIS (1963-2024) | U130: BIS (1963-2024) | V130: BIS (1963-2024) | W130: BIS (1966-2024) | X130: BIS (1966-2024) | Y130: National Source (1974-2024) | AA130: National Source (1950-1966); WEO 2002 (1967-1973); National Source (1974-2024) | AB130: National Source (1974-2024) | AC130: WEO 2025 (1950-2024)
A131: EUR | B131: 112 | C131: United Kingdom | D131: 2002 | E131: 112-2002 | F131: 218.64518 | G131: 83.445648 | H131: 135.19954 | I131: 154.38852 | J131: 75.019787 | K131: 79.36873 | L131: 35.712193 | N131: 35.434462 | O131: 35.001792 | P131: 1191.439 | Q131: OECD (1995-2024) | R131: OECD (1995-2024) | S131: OECD (1995-2024) | T131: BIS (1963-2024) | U131: BIS (1963-2024) | V131: BIS (1963-2024) | W131: BIS (1966-2024) | X131: BIS (1966-2024) | Y131: National Source (1974-2024) | AA131: National Source (1950-1966); WEO 2002 (1967-1973); National Source (1974-2024) | AB131: National Source (1974-2024) | AC131: WEO 2025 (1950-2024)
A132: EUR | B132: 112 | C132: United Kingdom | D132: 2003 | E132: 112-2003 | F132: 214.00201 | G132: 89.879396 | H132: 124.12261 | I132: 154.58734 | J132: 79.816646 | K132: 74.770689 | L132: 36.619133 | N132: 36.763689 | O132: 36.176325 | P132: 1258.334 | Q132: OECD (1995-2024) | R132: OECD (1995-2024) | S132: OECD (1995-2024) | T132: BIS (1963-2024) | U132: BIS (1963-2024) | V132: BIS (1963-2024) | W132: BIS (1966-2024) | X132: BIS (1966-2024) | Y132: National Source (1974-2024) | AA132: National Source (1950-1966); WEO 2002 (1967-1973); National Source (1974-2024) | AB132: National Source (1974-2024) | AC132: WEO 2025 (1950-2024)
A133: EUR | B133: 112 | C133: United Kingdom | D133: 2004 | E133: 112-2004 | F133: 217.74863 | G133: 95.636293 | H133: 122.11234 | I133: 158.15035 | J133: 85.375579 | K133: 72.774767 | L133: 39.672639 | N133: 39.801548 | O133: 39.048885 | P133: 1322.637 | Q133: OECD (1995-2024) | R133: OECD (1995-2024) | S133: OECD (1995-2024) | T133: BIS (1963-2024) | U133: BIS (1963-2024) | V133: BIS (1963-2024) | W133: BIS (1966-2024) | X133: BIS (1966-2024) | Y133: National Source (1974-2024) | AA133: National Source (1950-1966); WEO 2002 (1967-1973); National Source (1974-2024) | AB133: National Source (1974-2024) | AC133: WEO 2025 (1950-2024)
A134: EUR | B134: 112 | C134: United Kingdom | D134: 2005 | E134: 112-2005 | F134: 221.84259 | G134: 97.558104 | H134: 124.28449 | I134: 165.65002 | J134: 87.433771 | K134: 78.216249 | L134: 40.888179 | N134: 41.000423 | O134: 40.160887 | P134: 1398.749 | Q134: OECD (1995-2024) | R134: OECD (1995-2024) | S134: OECD (1995-2024) | T134: BIS (1963-2024) | U134: BIS (1963-2024) | V134: BIS (1963-2024) | W134: BIS (1966-2024) | X134: BIS (1966-2024) | Y134: National Source (1974-2024) | AA134: National Source (1950-1966); WEO 2002 (1967-1973); National Source (1974-2024) | AB134: National Source (1974-2024) | AC134: WEO 2025 (1950-2024)
A135: EUR | B135: 112 | C135: United Kingdom | D135: 2006 | E135: 112-2006 | F135: 223.0024 | G135: 103.97537 | H135: 119.02702 | I135: 172.1944 | J135: 91.59254 | K135: 80.601859 | L135: 42.056727 | N135: 42.058289 | O135: 41.117892 | P135: 1472.038 | Q135: OECD (1995-2024) | R135: OECD (1995-2024) | S135: OECD (1995-2024) | T135: BIS (1963-2024) | U135: BIS (1963-2024) | V135: BIS (1963-2024) | W135: BIS (1966-2024) | X135: BIS (1966-2024) | Y135: National Source (1974-2024) | AA135: National Source (1950-1966); WEO 2002 (1967-1973); National Source (1974-2024) | AB135: National Source (1974-2024) | AC135: WEO 2025 (1950-2024)
... A153: EUR | B153: 112 | C153: United Kingdom | D153: 2024 | E153: 112-2024 | F153: 156.5039 | G153: 80.821708 | H153: 75.682193 | I153: 137.32273 | J153: 76.17525 | K153: 61.147483 | L153: 100.16033 | N153: 101.28941 | O153: 100.71666 | P153: 2850.989 | Q153: OECD (1995-2024) | R153: OECD (1995-2024) | S153: OECD (1995-2024) | T153: BIS (1963-2024) | U153: BIS (1963-2024) | V153: BIS (1963-2024) | W153: BIS (1966-2024) | X153: BIS (1966-2024) | Y153: National Source (1974-2024) | AA153: National Source (1950-1966); WEO 2002 (1967-1973); National Source (1974-2024) | AB153: National Source (1974-2024) | AC153: WEO 2025 (1950-2024)
A154: EUR | B154: 122 | C154: Austria | D154: 1950 | E154: 122-1950 | I154: 19.479539 | O154: 21.041934 | P154: 3.9682665 | Q154: National Source (1995-2024) | R154: National Source (1995-2024) | S154: National Source (1995-2024) | T154: BIS (1950-2024) | U154: BIS (1950-2024) | V154: BIS (1950-2024) | W154: BIS (1995-2024) | X154: BIS (1995-2024) | AA154: WEO 2009 (1970-1987); WEO 2025 (1988-2024) | AB154: National Source (1950-2024) | AC154: PWT (1950-1964); WEO 2025 (1965-2024)
A155: EUR | B155: 122 | C155: Austria | D155: 1951 | E155: 122-1951 | I155: 19.465895 | O155: 14.518866 | P155: 5.2758942 | Q155: National Source (1995-2024) | R155: National Source (1995-2024) | S155: National Source (1995-2024) | T155: BIS (1950-2024) | U155: BIS (1950-2024) | V155: BIS (1950-2024) | W155: BIS (1995-2024) | X155: BIS (1995-2024) | AA155: WEO 2009 (1970-1987); WEO 2025 (1988-2024) | AB155: National Source (1950-2024) | AC155: PWT (1950-1964); WEO 2025 (1965-2024)
A156: EUR | B156: 122 | C156: Austria | D156: 1952 | E156: 122-1952 | I156: 17.439893 | O156: 12.912385 | P156: 6.118157 | Q156: National Source (1995-2024) | R156: National Source (1995-2024) | S156: National Source (1995-2024) | T156: BIS (1950-2024) | U156: BIS (1950-2024) | V156: BIS (1950-2024) | W156: BIS (1995-2024) | X156: BIS (1995-2024) | AA156: WEO 2009 (1970-1987); WEO 2025 (1988-2024) | AB156: National Source (1950-2024) | AC156: PWT (1950-1964); WEO 2025 (1965-2024)
A157: EUR | B157: 122 | C157: Austria | D157: 1953 | E157: 122-1953 | I157: 19.898267 | O157: 15.797825 | P157: 6.2920052 | Q157: National Source (1995-2024) | R157: National Source (1995-2024) | S157: National Source (1995-2024) | T157: BIS (1950-2024) | U157: BIS (1950-2024) | V157: BIS (1950-2024) | W157: BIS (1995-2024) | X157: BIS (1995-2024) | AA157: WEO 2009 (1970-1987); WEO 2025 (1988-2024) | AB157: National Source (1950-2024) | AC157: PWT (1950-1964); WEO 2025 (1965-2024)
A158: EUR | B158: 122 | C158: Austria | D158: 1954 | E158: 122-1954 | I158: 23.292787 | O158: 13.743311 | P158: 7.0579788 | Q158: National Source (1995-2024) | R158: National Source (1995-2024) | S158: National Source (1995-2024) | T158: BIS (1950-2024) | U158: BIS (1950-2024) | V158: BIS (1950-2024) | W158: BIS (1995-2024) | X158: BIS (1995-2024) | AA158: WEO 2009 (1970-1987); WEO 2025 (1988-2024) | AB158: National Source (1950-2024) | AC158: PWT (1950-1964); WEO 2025 (1965-2024)
A159: EUR | B159: 122 | C159: Austria | D159: 1955 | E159: 122-1955 | I159: 24.846695 | O159: 11.441094 | P159: 8.0936317 | Q159: National Source (1995-2024) | R159: National Source (1995-2024) | S159: National Source (1995-2024) | T159: BIS (1950-2024) | U159: BIS (1950-2024) | V159: BIS (1950-2024) | W159: BIS (1995-2024) | X159: BIS (1995-2024) | AA159: WEO 2009 (1970-1987); WEO 2025 (1988-2024) | AB159: National Source (1950-2024) | AC159: PWT (1950-1964); WEO 2025 (1965-2024)
A160: EUR | B160: 122 | C160: Austria | D160: 1956 | E160: 122-1956 | I160: 25.347849 | O160: 10.512523 | P160: 8.9987911 | Q160: National Source (1995-2024) | R160: National Source (1995-2024) | S160: National Source (1995-2024) | T160: BIS (1950-2024) | U160: BIS (1950-2024) | V160: BIS (1950-2024) | W160: BIS (1995-2024) | X160: BIS (1995-2024) | AA160: WEO 2009 (1970-1987); WEO 2025 (1988-2024) | AB160: National Source (1950-2024) | AC160: PWT (1950-1964); WEO 2025 (1965-2024)
A161: EUR | B161: 122 | C161: Austria | D161: 1957 | E161: 122-1957 | I161: 26.410275 | O161: 7.9903378 | P161: 9.9620319 | Q161: National Source (1995-2024) | R161: National Source (1995-2024) | S161: National Source (1995-2024) | T161: BIS (1950-2024) | U161: BIS (1950-2024) | V161: BIS (1950-2024) | W161: BIS (1995-2024) | X161: BIS (1995-2024) | AA161: WEO 2009 (1970-1987); WEO 2025 (1988-2024) | AB161: National Source (1950-2024) | AC161: PWT (1950-1964); WEO 2025 (1965-2024)
A162: EUR | B162: 122 | C162: Austria | D162: 1958 | E162: 122-1958 | I162: 28.412718 | O162: 10.97852 | P162: 10.347479 | Q162: National Source (1995-2024) | R162: National Source (1995-2024) | S162: National Source (1995-2024) | T162: BIS (1950-2024) | U162: BIS (1950-2024) | V162: BIS (1950-2024) | W162: BIS (1995-2024) | X162: BIS (1995-2024) | AA162: WEO 2009 (1970-1987); WEO 2025 (1988-2024) | AB162: National Source (1950-2024) | AC162: PWT (1950-1964); WEO 2025 (1965-2024)
A163: EUR | B163: 122 | C163: Austria | D163: 1959 | E163: 122-1959 | I163: 30.649069 | O163: 13.066517 | P163: 11.005228 | Q163: National Source (1995-2024) | R163: National Source (1995-2024) | S163: National Source (1995-2024) | T163: BIS (1950-2024) | U163: BIS (1950-2024) | V163: BIS (1950-2024) | W163: BIS (1995-2024) | X163: BIS (1995-2024) | AA163: WEO 2009 (1970-1987); WEO 2025 (1988-2024) | AB163: National Source (1950-2024) | AC163: PWT (1950-1964); WEO 2025 (1965-2024)
A164: EUR | B164: 122 | C164: Austria | D164: 1960 | E164: 122-1960 | I164: 32.783196 | O164: 13.201177 | P164: 12.286783 | Q164: National Source (1995-2024) | R164: National Source (1995-2024) | S164: National Source (1995-2024) | T164: BIS (1950-2024) | U164: BIS (1950-2024) | V164: BIS (1950-2024) | W164: BIS (1995-2024) | X164: BIS (1995-2024) | AA164: WEO 2009 (1970-1987); WEO 2025 (1988-2024) | AB164: National Source (1950-2024) | AC164: PWT (1950-1964); WEO 2025 (1965-2024)
A165: EUR | B165: 122 | C165: Austria | D165: 1961 | E165: 122-1961 | I165: 34.366523 | O165: 11.91275 | P165: 13.632453 | Q165: National Source (1995-2024) | R165: National Source (1995-2024) | S165: National Source (1995-2024) | T165: BIS (1950-2024) | U165: BIS (1950-2024) | V165: BIS (1950-2024) | W165: BIS (1995-2024) | X165: BIS (1995-2024) | AA165: WEO 2009 (1970-1987); WEO 2025 (1988-2024) | AB165: National Source (1950-2024) | AC165: PWT (1950-1964); WEO 2025 (1965-2024)
... A173: EUR | B173: 122 | C173: Austria | D173: 1969 | E173: 122-1969 | I173: 51.165407 | O173: 12.541045 | P173: 25.269026 | Q173: National Source (1995-2024) | R173: National Source (1995-2024) | S173: National Source (1995-2024) | T173: BIS (1950-2024) | U173: BIS (1950-2024) | V173: BIS (1950-2024) | W173: BIS (1995-2024) | X173: BIS (1995-2024) | AA173: WEO 2009 (1970-1987); WEO 2025 (1988-2024) | AB173: National Source (1950-2024) | AC173: PWT (1950-1964); WEO 2025 (1965-2024)
A174: EUR | B174: 122 | C174: Austria | D174: 1970 | E174: 122-1970 | I174: 53.226261 | N174: 18.649735 | O174: 12.057946 | P174: 28.371334 | Q174: National Source (1995-2024) | R174: National Source (1995-2024) | S174: National Source (1995-2024) | T174: BIS (1950-2024) | U174: BIS (1950-2024) | V174: BIS (1950-2024) | W174: BIS (1995-2024) | X174: BIS (1995-2024) | AA174: WEO 2009 (1970-1987); WEO 2025 (1988-2024) | AB174: National Source (1950-2024) | AC174: PWT (1950-1964); WEO 2025 (1965-2024)
A175: EUR | B175: 122 | C175: Austria | D175: 1971 | E175: 122-1971 | I175: 56.612508 | N175: 17.389201 | O175: 10.650033 | P175: 31.971733 | Q175: National Source (1995-2024) | R175: National Source (1995-2024) | S175: National Source (1995-2024) | T175: BIS (1950-2024) | U175: BIS (1950-2024) | V175: BIS (1950-2024) | W175: BIS (1995-2024) | X175: BIS (1995-2024) | AA175: WEO 2009 (1970-1987); WEO 2025 (1988-2024) | AB175: National Source (1950-2024) | AC175: PWT (1950-1964); WEO 2025 (1965-2024)
A176: EUR | B176: 122 | C176: Austria | D176: 1972 | E176: 122-1972 | I176: 59.965225 | N176: 16.681548 | O176: 9.9175573 | P176: 36.531173 | Q176: National Source (1995-2024) | R176: National Source (1995-2024) | S176: National Source (1995-2024) | T176: BIS (1950-2024) | U176: BIS (1950-2024) | V176: BIS (1950-2024) | W176: BIS (1995-2024) | X176: BIS (1995-2024) | AA176: WEO 2009 (1970-1987); WEO 2025 (1988-2024) | AB176: National Source (1950-2024) | AC176: PWT (1950-1964); WEO 2025 (1965-2024)
A177: EUR | B177: 122 | C177: Austria | D177: 1973 | E177: 122-1973 | I177: 58.720839 | N177: 16.69436 | O177: 9.8806665 | P177: 41.373727 | Q177: National Source (1995-2024) | R177: National Source (1995-2024) | S177: National Source (1995-2024) | T177: BIS (1950-2024) | U177: BIS (1950-2024) | V177: BIS (1950-2024) | W177: BIS (1995-2024) | X177: BIS (1995-2024) | AA177: WEO 2009 (1970-1987); WEO 2025 (1988-2024) | AB177: National Source (1950-2024) | AC177: PWT (1950-1964); WEO 2025 (1965-2024)
A178: EUR | B178: 122 | C178: Austria | D178: 1974 | E178: 122-1974 | I178: 59.052521 | N178: 16.821684 | O178: 9.4767786 | P178: 47.08351 | Q178: National Source (1995-2024) | R178: National Source (1995-2024) | S178: National Source (1995-2024) | T178: BIS (1950-2024) | U178: BIS (1950-2024) | V178: BIS (1950-2024) | W178: BIS (1995-2024) | X178: BIS (1995-2024) | AA178: WEO 2009 (1970-1987); WEO 2025 (1988-2024) | AB178: National Source (1950-2024) | AC178: PWT (1950-1964); WEO 2025 (1965-2024)
A179: EUR | B179: 122 | C179: Austria | D179: 1975 | E179: 122-1975 | I179: 62.949228 | N179: 22.841119 | O179: 14.595704 | P179: 49.973607 | Q179: National Source (1995-2024) | R179: National Source (1995-2024) | S179: National Source (1995-2024) | T179: BIS (1950-2024) | U179: BIS (1950-2024) | V179: BIS (1950-2024) | W179: BIS (1995-2024) | X179: BIS (1995-2024) | AA179: WEO 2009 (1970-1987); WEO 2025 (1988-2024) | AB179: National Source (1950-2024) | AC179: PWT (1950-1964); WEO 2025 (1965-2024)
A180: EUR | B180: 122 | C180: Austria | D180: 1976 | E180: 122-1976 | I180: 69.356693 | N180: 26.188977 | O180: 17.616872 | P180: 55.185734 | Q180: National Source (1995-2024) | R180: National Source (1995-2024) | S180: National Source (1995-2024) | T180: BIS (1950-2024) | U180: BIS (1950-2024) | V180: BIS (1950-2024) | W180: BIS (1995-2024) | X180: BIS (1995-2024) | AA180: WEO 2009 (1970-1987); WEO 2025 (1988-2024) | AB180: National Source (1950-2024) | AC180: PWT (1950-1964); WEO 2025 (1965-2024)
A181: EUR | B181: 122 | C181: Austria | D181: 1977 | E181: 122-1977 | I181: 72.016026 | N181: 28.489775 | O181: 19.592487 | P181: 61.048911 | Q181: National Source (1995-2024) | R181: National Source (1995-2024) | S181: National Source (1995-2024) | T181: BIS (1950-2024) | U181: BIS (1950-2024) | V181: BIS (1950-2024) | W181: BIS (1995-2024) | X181: BIS (1995-2024) | AA181: WEO 2009 (1970-1987); WEO 2025 (1988-2024) | AB181: National Source (1950-2024) | AC181: PWT (1950-1964); WEO 2025 (1965-2024)
A182: EUR | B182: 122 | C182: Austria | D182: 1978 | E182: 122-1978 | I182: 78.471191 | N182: 32.150983 | O182: 22.454026 | P182: 64.4606 | Q182: National Source (1995-2024) | R182: National Source (1995-2024) | S182: National Source (1995-2024) | T182: BIS (1950-2024) | U182: BIS (1950-2024) | V182: BIS (1950-2024) | W182: BIS (1995-2024) | X182: BIS (1995-2024) | AA182: WEO 2009 (1970-1987); WEO 2025 (1988-2024) | AB182: National Source (1950-2024) | AC182: PWT (1950-1964); WEO 2025 (1965-2024)
A183: EUR | B183: 122 | C183: Austria | D183: 1979 | E183: 122-1979 | I183: 83.736777 | N183: 34.129521 | O183: 23.855336 | P183: 70.340658 | Q183: National Source (1995-2024) | R183: National Source (1995-2024) | S183: National Source (1995-2024) | T183: BIS (1950-2024) | U183: BIS (1950-2024) | V183: BIS (1950-2024) | W183: BIS (1995-2024) | X183: BIS (1995-2024) | AA183: WEO 2009 (1970-1987); WEO 2025 (1988-2024) | AB183: National Source (1950-2024) | AC183: PWT (1950-1964); WEO 2025 (1965-2024)
A184: EUR | B184: 122 | C184: Austria | D184: 1980 | E184: 122-1980 | I184: 87.977617 | N184: 35.591785 | O184: 25.11888 | P184: 75.564675 | Q184: National Source (1995-2024) | R184: National Source (1995-2024) | S184: National Source (1995-2024) | T184: BIS (1950-2024) | U184: BIS (1950-2024) | V184: BIS (1950-2024) | W184: BIS (1995-2024) | X184: BIS (1995-2024) | AA184: WEO 2009 (1970-1987); WEO 2025 (1988-2024) | AB184: National Source (1950-2024) | AC184: PWT (1950-1964); WEO 2025 (1965-2024)
A185: EUR | B185: 122 | C185: Austria | D185: 1981 | E185: 122-1981 | I185: 91.982357 | N185: 37.474346 | O185: 26.676164 | P185: 80.4426 | Q185: National Source (1995-2024) | R185: National Source (1995-2024) | S185: National Source (1995-2024) | T185: BIS (1950-2024) | U185: BIS (1950-2024) | V185: BIS (1950-2024) | W185: BIS (1995-2024) | X185: BIS (1995-2024) | AA185: WEO 2009 (1970-1987); WEO 2025 (1988-2024) | AB185: National Source (1950-2024) | AC185: PWT (1950-1964); WEO 2025 (1965-2024)
... A198: EUR | B198: 122 | C198: Austria | D198: 1994 | E198: 122-1994 | I198: 111.42509 | N198: 64.071427 | O198: 53.016424 | P198: 168.00077 | Q198: National Source (1995-2024) | R198: National Source (1995-2024) | S198: National Source (1995-2024) | T198: BIS (1950-2024) | U198: BIS (1950-2024) | V198: BIS (1950-2024) | W198: BIS (1995-2024) | X198: BIS (1995-2024) | AA198: WEO 2009 (1970-1987); WEO 2025 (1988-2024) | AB198: National Source (1950-2024) | AC198: PWT (1950-1964); WEO 2025 (1965-2024)
A199: EUR | B199: 122 | C199: Austria | D199: 1995 | E199: 122-1995 | F199: 124.38977 | G199: 42.410044 | H199: 81.97973 | I199: 112.87858 | J199: 43.18391 | K199: 69.694672 | N199: 68.238169 | O199: 55.552107 | P199: 175.6117 | Q199: National Source (1995-2024) | R199: National Source (1995-2024) | S199: National Source (1995-2024) | T199: BIS (1950-2024) | U199: BIS (1950-2024) | V199: BIS (1950-2024) | W199: BIS (1995-2024) | X199: BIS (1995-2024) | AA199: WEO 2009 (1970-1987); WEO 2025 (1988-2024) | AB199: National Source (1950-2024) | AC199: PWT (1950-1964); WEO 2025 (1965-2024)
A200: EUR | B200: 122 | C200: Austria | D200: 1996 | E200: 122-1996 | F200: 125.17276 | G200: 43.17075 | H200: 82.002006 | I200: 114.46338 | J200: 43.975523 | K200: 70.48786 | N200: 68.180321 | O200: 55.91767 | P200: 181.5419 | Q200: National Source (1995-2024) | R200: National Source (1995-2024) | S200: National Source (1995-2024) | T200: BIS (1950-2024) | U200: BIS (1950-2024) | V200: BIS (1950-2024) | W200: BIS (1995-2024) | X200: BIS (1995-2024) | AA200: WEO 2009 (1970-1987); WEO 2025 (1988-2024) | AB200: National Source (1950-2024) | AC200: PWT (1950-1964); WEO 2025 (1965-2024)
A201: EUR | B201: 122 | C201: Austria | D201: 1997 | E201: 122-1997 | F201: 130.19315 | G201: 43.303633 | H201: 86.889514 | I201: 118.91125 | J201: 44.090198 | K201: 74.821053 | N201: 63.373173 | O201: 57.12043 | P201: 187.7787 | Q201: National Source (1995-2024) | R201: National Source (1995-2024) | S201: National Source (1995-2024) | T201: BIS (1950-2024) | U201: BIS (1950-2024) | V201: BIS (1950-2024) | W201: BIS (1995-2024) | X201: BIS (1995-2024) | AA201: WEO 2009 (1970-1987); WEO 2025 (1988-2024) | AB201: National Source (1950-2024) | AC201: PWT (1950-1964); WEO 2025 (1965-2024)
A202: EUR | B202: 122 | C202: Austria | D202: 1998 | E202: 122-1998 | F202: 130.61914 | G202: 42.659414 | H202: 87.959724 | I202: 119.77287 | J202: 43.416809 | K202: 76.356065 | N202: 69.196552 | O202: 57.151826 | P202: 195.2746 | Q202: National Source (1995-2024) | R202: National Source (1995-2024) | S202: National Source (1995-2024) | T202: BIS (1950-2024) | U202: BIS (1950-2024) | V202: BIS (1950-2024) | W202: BIS (1995-2024) | X202: BIS (1995-2024) | AA202: WEO 2009 (1970-1987); WEO 2025 (1988-2024) | AB202: National Source (1950-2024) | AC202: PWT (1950-1964); WEO 2025 (1965-2024)
A203: EUR | B203: 122 | C203: Austria | D203: 1999 | E203: 122-1999 | F203: 137.0246 | G203: 44.659592 | H203: 92.365006 | I203: 125.71935 | J203: 45.445547 | K203: 80.273804 | N203: 61.339556 | O203: 58.096669 | P203: 203.065 | Q203: National Source (1995-2024) | R203: National Source (1995-2024) | S203: National Source (1995-2024) | T203: BIS (1950-2024) | U203: BIS (1950-2024) | V203: BIS (1950-2024) | W203: BIS (1995-2024) | X203: BIS (1995-2024) | AA203: WEO 2009 (1970-1987); WEO 2025 (1988-2024) | AB203: National Source (1950-2024) | AC203: PWT (1950-1964); WEO 2025 (1965-2024)
A204: EUR | B204: 122 | C204: Austria | D204: 2000 | E204: 122-2000 | F204: 144.38945 | G204: 45.404855 | H204: 98.98459 | I204: 133.01316 | J204: 45.239606 | K204: 87.773555 | N204: 66.108882 | O204: 56.827277 | P204: 212.4068 | Q204: National Source (1995-2024) | R204: National Source (1995-2024) | S204: National Source (1995-2024) | T204: BIS (1950-2024) | U204: BIS (1950-2024) | V204: BIS (1950-2024) | W204: BIS (1995-2024) | X204: BIS (1995-2024) | AA204: WEO 2009 (1970-1987); WEO 2025 (1988-2024) | AB204: National Source (1950-2024) | AC204: PWT (1950-1964); WEO 2025 (1965-2024)
A205: EUR | B205: 122 | C205: Austria | D205: 2001 | E205: 122-2001 | F205: 146.71703 | G205: 45.678759 | H205: 101.03828 | I205: 134.74292 | J205: 45.505994 | K205: 89.236931 | N205: 67.238356 | O205: 55.345386 | P205: 219.3733 | Q205: National Source (1995-2024) | R205: National Source (1995-2024) | S205: National Source (1995-2024) | T205: BIS (1950-2024) | U205: BIS (1950-2024) | V205: BIS (1950-2024) | W205: BIS (1995-2024) | X205: BIS (1995-2024) | AA205: WEO 2009 (1970-1987); WEO 2025 (1988-2024) | AB205: National Source (1950-2024) | AC205: PWT (1950-1964); WEO 2025 (1965-2024)
A206: EUR | B206: 122 | C206: Austria | D206: 2002 | E206: 122-2002 | F206: 147.51393 | G206: 46.608014 | H206: 100.90591 | I206: 134.46702 | J206: 46.39432 | K206: 88.072704 | N206: 67.44032 | O206: 55.068709 | P206: 225.0879 | Q206: National Source (1995-2024) | R206: National Source (1995-2024) | S206: National Source (1995-2024) | T206: BIS (1950-2024) | U206: BIS (1950-2024) | V206: BIS (1950-2024) | W206: BIS (1995-2024) | X206: BIS (1995-2024) | AA206: WEO 2009 (1970-1987); WEO 2025 (1988-2024) | AB206: National Source (1950-2024) | AC206: PWT (1950-1964); WEO 2025 (1965-2024)
...

Sheet countrylist
A1: country | B1: ifscode | C1: dept
A2: Afghanistan | B2: 512 | C2: MCD
A3: Albania | B3: 914 | C3: EUR
A4: Algeria | B4: 612 | C4: MCD
A5: Angola | B5: 614 | C5: AFR
A6: Antigua and Barbuda | B6: 311 | C6: WHD
A7: Argentina | B7: 213 | C7: WHD
A8: Armenia | B8: 911 | C8: MCD
A9: Australia | B9: 193 | C9: APD
A10: Austria | B10: 122 | C10: EUR
A11: Azerbaijan | B11: 912 | C11: MCD
A12: Bahamas, The | B12: 313 | C12: WHD
A13: Bahrain | B13: 419 | C13: MCD
... A191: Zimbabwe | B191: 698 | C191: AFR

Sheet weo gov cov
A1: ifscode | B1: country | C1: dept | D1: weo gov coverage | E1: ps/nfps
A2: 622 | B2: Cameroon | C2: =VLOOKUP(A2,[1]countrylist!$B$1:$C$191,2,0) -> AFR | D2: CG, NFPC | F2: change to CG
A3: 628 | B3: Chad | C3: =VLOOKUP(A3,[1]countrylist!$B$1:$C$191,2,0) -> AFR | D3: CG, NFPC | F3: change to CG
A4: 644 | B4: Ethiopia | C4: =VLOOKUP(A4,[1]countrylist!$B$1:$C$191,2,0) -> AFR | D4: CG, SG, LG, NFPC | F4: change to GG
A5: 684 | B5: Mauritius | C5: =VLOOKUP(A5,[1]countrylist!$B$1:$C$191,2,0) -> AFR | D5: NFPS - CG, LG, NFPC | E5: NFPS
A6: 694 | B6: Nigeria | C6: =VLOOKUP(A6,[1]countrylist!$B$1:$C$191,2,0) -> AFR | D6: CG, SG, LG, NFPC | F6: keep CG
A7: 369 | B7: Trinidad & Tobago | C7: =VLOOKUP(A7,[1]countrylist!$B$1:$C$191,2,0) -> AFR | D7: CG, NFPC | F7: change to CG
A8: 941 | B8: Latvia | C8: =VLOOKUP(A8,[1]countrylist!$B$1:$C$191,2,0) -> EUR | D8: CG, LG, SS, NFPC | F8: drop NFPS
A9: 439 | B9: Jordan | C9: =VLOOKUP(A9,[1]countrylist!$B$1:$C$191,2,0) -> MCD | D9: CG, NFPC | F9: change to CG
A10: 316 | B10: Barbados | C10: =VLOOKUP(A10,[1]countrylist!$B$1:$C$191,2,0) -> WHD | D10: CG, SS, NFPC | E10: NFPS
A11: 248 | B11: Ecuador | C11: =VLOOKUP(A11,[1]countrylist!$B$1:$C$191,2,0) -> WHD | D11: CG, SG, LG, SS, NFPC | E11: NFPS | F11: drop GG
A12: 268 | B12: Honduras | C12: =VLOOKUP(A12,[1]countrylist!$B$1:$C$191,2,0) -> WHD | D12: CG, LG, SS, NFPC | E12: NFPS
A13: 283 | B13: Panama | C13: =VLOOKUP(A13,[1]countrylist!$B$1:$C$191,2,0) -> WHD | D13: CG, SG, LG, SS, NFPC | E13: NFPS | F13: need to find out
A14: 299 | B14: Venezuela, Republica Bolivariana de | C14: =VLOOKUP(A14,[1]countrylist!$B$1:$C$191,2,0) -> WHD | D14: CG, LG, SS, BCG, NFPC | F14: drop NFPS
A15: 914 | B15: Albania | C15: =VLOOKUP(A15,[1]countrylist!$B$1:$C$191,2,0) -> EUR | D15: CG, LG, SS, MPC, NFPC | F15: drop PS
A16: 944 | B16: Hungary | C16: =VLOOKUP(A16,[1]countrylist!$B$1:$C$191,2,0) -> EUR | D16: CG, LG, SS, NMPC | F16: drop PS
A17: 469 | B17: Egypt | C17: =VLOOKUP(A17,[1]countrylist!$B$1:$C$191,2,0) -> MCD | D17: CG, LG, SS, MPC | F17: drop PS
A18: 339 | B18: Belize | C18: =VLOOKUP(A18,[1]countrylist!$B$1:$C$191,2,0) -> WHD | D18: CG, MPC | F18: change to CG
A19: 218 | B19: Bolivia | C19: =VLOOKUP(A19,[1]countrylist!$B$1:$C$191,2,0) -> WHD | D19: CG, LG, SS, MPC, NMPC, NFPC | E19: PS | F19: drop GG
A20: 223 | B20: Brazil | C20: =VLOOKUP(A20,[1]countrylist!$B$1:$C$191,2,0) -> WHD | D20: CG, SG, LG, SS, MPC, NFPC | E20: NFPS
A21: 243 | B21: Dominican Republic | C21: =VLOOKUP(A21,[1]countrylist!$B$1:$C$191,2,0) -> WHD | D21: CG, SG, LG, SS, NMPC | E21: NFPS
A22: 273 | B22: Mexico | C22: =VLOOKUP(A22,[1]countrylist!$B$1:$C$191,2,0) -> WHD | D22: CG, SS, NMPC, NFPC | E22: PS
A23: 288 | B23: Paraguay | C23: =VLOOKUP(A23,[1]countrylist!$B$1:$C$191,2,0) -> WHD | D23: CG, SG, LG, SS, MPC, NFPC | E23: PS
A24: 298 | B24: Uruguay | C24: =VLOOKUP(A24,[1]countrylist!$B$1:$C$191,2,0) -> WHD | D24: CG, LG, SS, MPC, NFPC | E24: PS | F24: drop GG
A25: 636 | B25: Congo, Dem. Rep. of | C25: =VLOOKUP(A25,[1]countrylist!$B$1:$C$191,2,0) -> AFR | D25: CG, LG
A26: 634 | B26: Congo, Republic of | C26: =VLOOKUP(A26,[1]countrylist!$B$1:$C$191,2,0) -> AFR | D26: CG
A27: 662 | B27: Cote D'Ivoire | C27: =VLOOKUP(A27,[1]countrylist!$B$1:$C$191,2,0) -> AFR | D27: CG
A28: 648 | B28: Gambia, The | C28: =VLOOKUP(A28,[1]countrylist!$B$1:$C$191,2,0) -> AFR | D28: CG
A29: 716 | B29: São Tomé and Príncipe | C29: =VLOOKUP(A29,[1]countrylist!$B$1:$C$191,2,0) -> AFR | D29: CG
A30: 614 | B30: Angola | C30: =VLOOKUP(A30,[1]countrylist!$B$1:$C$191,2,0) -> AFR | D30: CG, LG
A31: 638 | B31: Benin | C31: =VLOOKUP(A31,[1]countrylist!$B$1:$C$191,2,0) -> AFR | D31: CG
A32: 616 | B32: Botswana | C32: =VLOOKUP(A32,[1]countrylist!$B$1:$C$191,2,0) -> AFR | D32: CG
A33: 748 | B33: Burkina Faso | C33: =VLOOKUP(A33,[1]countrylist!$B$1:$C$191,2,0) -> AFR | D33: CG
A34: 618 | B34: Burundi | C34: =VLOOKUP(A34,[1]countrylist!$B$1:$C$191,2,0) -> AFR | D34: CG
A35: 624 | B35: Cape Verde | C35: =VLOOKUP(A35,[1]countrylist!$B$1:$C$191,2,0) -> AFR | D35: CG, SS
A36: 626 | B36: C.A.R. | C36: =VLOOKUP(A36,[1]countrylist!$B$1:$C$191,2,0) -> AFR | D36: CG
... A189: 111 | B189: United States | C189: =VLOOKUP(A189,[1]countrylist!$B$1:$C$191,2,0) -> WHD | D189: CG, SG, LG

Sheet footnote
A1: dept | B1: ifscode | C1: national source | D1: NS | E1: source | F1: url | G1: count
A2: =VLOOKUP(B2,countrylist!$B$1:$C$191,2,0) -> AFR | B2: 664 | C2: Kenya | D2: 1 | E2: Central Bank of Kenya | F2: https://www.centralbank.go.ke/public-debt/ | G2: 1
A3: =VLOOKUP(B3,countrylist!$B$1:$C$191,2,0) -> WHD | B3: 223 | C3: Brazil | D3: 1 | E3: Central Bank of Brazil | F3: http://www.bcb.gov.br/ingles/economic/seriehistNPDGross2007.asp | G3: 1
A4: =VLOOKUP(B4,countrylist!$B$1:$C$191,2,0) -> WHD | B4: 361 | C4: St. Kitts and Nevis | D4: 1 | E4: St. Kitts and Nevis Ministry of Finance | F4: https://www.eccb-centralbank.org/statistics/monetary-survey-datas/country-report | G4: 1
A5: =VLOOKUP(B5,countrylist!$B$1:$C$191,2,0) -> WHD | B5: 364 | C5: St. Vincent and the Grenadines | D5: 1 | E5: St. Vincent and the Grenadines Ministry of Finance | G5: 1
A6: =VLOOKUP(B6,countrylist!$B$1:$C$191,2,0) -> MCD | B6: 915 | C6: Georgia | D6: 1 | E6: Georgia Ministry of Finance | F6: http://mof.ge/en/4411 | G6: 1
A7: =VLOOKUP(B7,countrylist!$B$1:$C$191,2,0) -> MCD | B7: 916 | C7: Kazakhstan | D7: 1 | E7: Kazakhstan National Bank, Kazakhstan Ministry of Finance, and Kazakhstan Ministry of National Economy | G7: 3
A8: =VLOOKUP(B8,countrylist!$B$1:$C$191,2,0) -> EUR | B8: 939 | C8: Estonia | D8: 1 | E8: Statistics Estonia | F8: http://pub.stat.ee/px-web.2001/I_Databas/Economy/08Finance/06Government_finances/04Revenue_expenditure_and_debt/04Revenue_expenditure_and_debt.asp | G8: 1
A9: =VLOOKUP(B9,countrylist!$B$1:$C$191,2,0) -> AFR | B9: 714 | C9: Rwanda | E9: Central government debt excludes debt of extra-budgetary units, local governments and does not consolidate with budgetary central government debt held by the Rwanda Social Security Board. In addition, it also excludes guarantees extended by the budgetary central government. | G9: 0
A10: =VLOOKUP(B10,countrylist!$B$1:$C$191,2,0) -> AFR | B10: 684 | C10: Mauritius | D10: 1 | E10: Republic of Mauritius Ministry of Finance and Economic Development, and Statistics Mauritius | G10: 2
A11: =VLOOKUP(B11,countrylist!$B$1:$C$191,2,0) -> AFR | B11: 614 | C11: Angola | E11: Central government debt includes two state-owned enterprises (Sonangol and TAAG) | G11: 0
A12: =VLOOKUP(B12,countrylist!$B$1:$C$191,2,0) -> AFR | B12: 199 | C12: South Africa | D12: 1 | E12: South African Reserve Bank (via CEIC) | F12: https://www.ceicdata.com/en | G12: 1
A13: =VLOOKUP(B13,countrylist!$B$1:$C$191,2,0) -> APD | B13: 819 | C13: Fiji | D13: 1 | E13: Ministry of Economy and Reserve Bank of Fiji | G13: 1
A14: =VLOOKUP(B14,countrylist!$B$1:$C$191,2,0) -> APD | B14: 924 | C14: China, Mainland | D14: 1 | E14: People's Bank of China | G14: 1
A15: =VLOOKUP(B15,countrylist!$B$1:$C$191,2,0) -> APD | B15: 534 | C15: India | D15: 1 | E15: Ministry of Finance India, and Reserve Bank of India | G15: 2
A16: =VLOOKUP(B16,countrylist!$B$1:$C$191,2,0) -> APD | B16: 536 | C16: Indonesia | D16: 1 | E16: Ministry of Finance Republic of Indonesia (via CEIC) | F16: https://www.ceicdata.com/en | G16: 1
A17: =VLOOKUP(B17,countrylist!$B$1:$C$191,2,0) -> APD | B17: 158 | C17: Japan | D17: 1 | E17: Bank of Japan, and the Cabinet Office | G17: 2
A18: =VLOOKUP(B18,countrylist!$B$1:$C$191,2,0) -> APD | B18: 542 | C18: Korea, Republic of | D18: 1 | E18: Republic of Korea Ministry of Strategy and Finance | G18: 1
A19: =VLOOKUP(B19,countrylist!$B$1:$C$191,2,0) -> APD | B19: 548 | C19: Malaysia | D19: 1 | E19: Ministry of Finance Malaysia | F19: http://www.treasury.gov.my/index.php/en/economy/economic-data.html | G19: 1
A20: =VLOOKUP(B20,countrylist!$B$1:$C$191,2,0) -> APD | B20: 516 | C20: Brunei Darussalam | E20: The central government debt for 2001-2005 only includes data from IFS and from 2006 onwards, it covers issuance of sukuk for the purpose of benchmarking corporate sukuk only and not for fiscal deficit financing. | G20: 0
A21: =VLOOKUP(B21,countrylist!$B$1:$C$191,2,0) -> APD | B21: 948 | C21: Mongolia | D21: 1 | E21: Mongolia Ministry of Finance | F21: http://shilendans.gov.mn/org/408?form=1620896&year=2017&group=3&task=739 | G21: 1
A22: =VLOOKUP(B22,countrylist!$B$1:$C$191,2,0) -> APD | B22: 196 | C22: New Zealand | D22: 1 | E22: Statistics New Zealand | F22: http://www.stats.govt.nz/browse_for_stats/economic_indicators/NationalAccounts/long-term-data-series/government.aspx | G22: 1
A23: =VLOOKUP(B23,countrylist!$B$1:$C$191,2,0) -> APD | B23: 862 | C23: Samoa | D23: 1 | E23: Central Bank of Samoa | G23: 1
A24: =VLOOKUP(B24,countrylist!$B$1:$C$191,2,0) -> APD | B24: 576 | C24: Singapore | D24: 1 | E24: Singapore Ministry of Finance | G24: 1
A25: =VLOOKUP(B25,countrylist!$B$1:$C$191,2,0) -> APD | B25: 813 | C25: Solomon Islands | D25: 1 | E25: Central Bank of Solomon Islands | F25: http://www.cbsi.com.sb/publications/quarterly-review/ | G25: 1
A26: =VLOOKUP(B26,countrylist!$B$1:$C$191,2,0) -> APD | B26: 528 | C26: Taiwan Province of China | D26: 1 | E26: Ministry of Finance Republic of China, Taiwan (via CEIC) | F26: https://www.ceicdata.com/en | G26: 1
A27: =VLOOKUP(B27,countrylist!$B$1:$C$191,2,0) -> APD | B27: 578 | C27: Thailand | D27: 1 | E27: Bank of Thailand | F27: http://www2.bot.or.th/statistics/ReportPage.aspx?reportID=775&language=eng | G27: 1
A28: =VLOOKUP(B28,countrylist!$B$1:$C$191,2,0) -> APD | B28: 537 | C28: Timor Leste | D28: 1 | E28: Central Bank of Timor-Leste | G28: 1
A29: =VLOOKUP(B29,countrylist!$B$1:$C$191,2,0) -> APD | B29: 582 | C29: Vietnam | D29: 1 | E29: Ministry of Finance Vietnam (via CEIC) | F29: https://www.ceicdata.com/en | G29: 1
A30: =VLOOKUP(B30,countrylist!$B$1:$C$191,2,0) -> EUR | B30: 914 | C30: Albania | D30: 1 | E30: Bank of Albania | F30: https://www.bankofalbania.org/web/Time_series_22_2.php?evn=agregate_detaje&evb=agregate&cregtab_id=434&periudha_id=1; https://www.bankofalbania.org/web/Time_series_22_2.php?evn=agregate_detaje&evb=agregate&cregtab_id=702&periudha_id=3 | G30: 1
A31: =VLOOKUP(B31,countrylist!$B$1:$C$191,2,0) -> EUR | B31: 122 | C31: Austria | D31: 1 | E31: Austrian National Bank | F31: https://www.oenb.at/isaweb/report.do;jsessionid=E41DFAB747B318A6699E887D7289C517?report=7.21 | G31: 1
A32: =VLOOKUP(B32,countrylist!$B$1:$C$191,2,0) -> EUR | B32: 913 | C32: Belarus | D32: 1 | E32: Ministry of Finance of the Republic of Belarus (via CEIC) | F32: https://www.ceicdata.com/en | G32: 1
A33: =VLOOKUP(B33,countrylist!$B$1:$C$191,2,0) -> EUR | B33: 124 | C33: Belgium | D33: 1 | E33: National Bank of Belgium | F33: http://stat.nbb.be/Index.aspx?ThemeTreeId=10&lang=fr# | G33: 1
A34: =VLOOKUP(B34,countrylist!$B$1:$C$191,2,0) -> EUR | B34: 960 | C34: Croatia | D34: 1 | E34: Croatian National Bank (via CEIC) | F34: https://www.ceicdata.com/en | G34: 1
A35: =VLOOKUP(B35,countrylist!$B$1:$C$191,2,0) -> EUR | B35: 423 | C35: Cyprus | D35: 1 | E35: Central Bank of Cyprus | G35: 1
A36: =VLOOKUP(B36,countrylist!$B$1:$C$191,2,0) -> EUR | B36: 935 | C36: Czech Republic | D36: 1 | E36: Ministry of Finance of the Czech Republic (via CEIC), and Czech Statistical Office | F36: https://www.ceicdata.com/en | G36: 2
A37: =VLOOKUP(B37,countrylist!$B$1:$C$191,2,0) -> EUR | B37: 128 | C37: Denmark | D37: 1 | E37: Denmark National Bank | G37: 1
A38: =VLOOKUP(B38,countrylist!$B$1:$C$191,2,0) -> EUR | B38: 172 | C38: Finland | D38: 1 | E38: Treasury Finland | F38: http://www.treasuryfinland.fi/verti/?bmark=/DATABASE/0VALTION%20VELANHALLINTA/0VALTIONVELKA/Valtionvelka_BKT&gfile=/QUICKTABLES/0VALTION%20VELANHALLINTA/0VALTIONVELKA/Valtionvelka_BKT&ACTION=OPENROOT&lang=en | G38: 1
A39: =VLOOKUP(B39,countrylist!$B$1:$C$191,2,0) -> EUR | B39: 132 | C39: France | D39: 1 | E39: National Institute of Statistics and Economic Studies | F39: https://www.insee.fr/fr/statistiques | G39: 1
A40: =VLOOKUP(B40,countrylist!$B$1:$C$191,2,0) -> EUR | B40: 134 | C40: Germany | D40: 1 | E40: Bundesbank | G40: 1
A41: =VLOOKUP(B41,countrylist!$B$1:$C$191,2,0) -> EUR | B41: 174 | C41: Greece | D41: 1 | E41: Ministry of Finance Greece (via CEIC) | F41: https://www.ceicdata.com/en | G41: 1
A42: =VLOOKUP(B42,countrylist!$B$1:$C$191,2,0) -> EUR | B42: 944 | C42: Hungary | D42: 1 | E42: National Bank of Hungary (via CEIC) | F42: https://www.ceicdata.com/en | G42: 1
A43: =VLOOKUP(B43,countrylist!$B$1:$C$191,2,0) -> EUR | B43: 176 | C43: Iceland | D43: 1 | E43: Statistics Iceland, and Central Bank of Iceland | F43: https://www.statice.is/; http://px.hagstofa.is/pxen/pxweb/en/Efnahagur/Efnahagur__fjaropinber__fjarmal_rikissjods/THJ05281.px/table/tableViewLayout1/?rxid=a676e0a2-51c5-43ed-9327-ec42fd5a2e6f | G43: 2
A44: =VLOOKUP(B44,countrylist!$B$1:$C$191,2,0) -> EUR | B44: 178 | C44: Ireland | D44: 1 | E44: Ireland National Treasury Management Agency (via CEIC), Central Bank of Ireland, and Central Statistics Office Ireland | F44: https://www.ceicdata.com/en | G44: 3
A45: =VLOOKUP(B45,countrylist!$B$1:$C$191,2,0) -> EUR | B45: 436 | C45: Israel | D45: 1 | E45: Bank of Israel | F45: http://www.boi.org.il/en/DataAndStatistics/Pages/MainPage.aspx?Level=2&Sid=19&SubjectType=2 | G45: 1
A46: =VLOOKUP(B46,countrylist!$B$1:$C$191,2,0) -> EUR | B46: 136 | C46: Italy | D46: 1 | E46: Bank of Italy | F46: https://infostat.bancaditalia.it/inquiry | G46: 1
A47: =VLOOKUP(B47,countrylist!$B$1:$C$191,2,0) -> EUR | B47: 941 | C47: Latvia | D47: 1 | E47: Republic of Latvia Treasury | F47: http://www.kase.gov.lv/l/saimnieciska-gada-parskats-par-valsts-budzeta-izpildi-un-pasvaldibu-budzetiem/86 http://www.kase.gov.lv/?object_id=9151 | G47: 1
A48: =VLOOKUP(B48,countrylist!$B$1:$C$191,2,0) -> APD | B48: 193 | C48: Australia | E48: From 1988-2016, private credit uses a proxy debt series which covers loans, debt securities and financial derivatives. | G48: 0
A49: =VLOOKUP(B49,countrylist!$B$1:$C$191,2,0) -> EUR | B49: 137 | C49: Luxembourg | D49: 1 | E49: Central Bank of Luxembourg, and Luxembourg State Treasury | F49: http://www.bcl.lu/en/statistics/series_statistiques_luxembourg/05_real_economy/index.html; http://www.te.public.lu/fr/dette_publique/moyen_long_terme/Evolution_historique_de_la_dette_publique_de_1970-2012.html | G49: 2
A50: =VLOOKUP(B50,countrylist!$B$1:$C$191,2,0) -> EUR | B50: 962 | C50: Macedonia, FYR | D50: 1 | E50: National Bank of the Republic of Macedonia | F50: http://www.nbrm.mk/?ItemID=E93CE394DF9E684F9356289B19564FD5 | G50: 1
A51: =VLOOKUP(B51,countrylist!$B$1:$C$191,2,0) -> EUR | B51: 181 | C51: Malta | D51: 1 | E51: Central Bank of Malta | F51: https://www.centralbankmalta.org/government-finance | G51: 1
A52: =VLOOKUP(B52,countrylist!$B$1:$C$191,2,0) -> EUR | B52: 921 | C52: Moldova | D52: 1 | E52: Ministry of Finance of the Republic of Moldova (via CEIC) | F52: https://www.ceicdata.com/en | G52: 1
A53: =VLOOKUP(B53,countrylist!$B$1:$C$191,2,0) -> EUR | B53: 138 | C53: Netherlands | D53: 1 | E53: Central Bank of the Netherlands | F53: https://www.dnb.nl/en/statistics/statistics-dnb/key-statistics-dutch-economy/national-summary-data-page-sdds/index.jsp | G53: 1
A54: =VLOOKUP(B54,countrylist!$B$1:$C$191,2,0) -> EUR | B54: 142 | C54: Norway | D54: 1 | E54: Statistics Norway | F54: https://www.ssb.no/statistikkbanken/SelectVarVal/Define.asp?MainTable=OffBruttoGjeld&KortNavnWeb=offogjeld&PLanguage=1&checked=true | G54: 1
A55: =VLOOKUP(B55,countrylist!$B$1:$C$191,2,0) -> EUR | B55: 964 | C55: Poland | D55: 1 | E55: Ministry of Finance Poland | F55: http://www.mf.gov.pl/en/web/wp/public-debt/outstanding-debt/historical-data | G55: 1
A56: =VLOOKUP(B56,countrylist!$B$1:$C$191,2,0) -> EUR | B56: 182 | C56: Portugal | D56: 1 | E56: Banco de Portugal, except for historical data up to 1994, in which it refers to the Portuguese Treasury and Debt Management Agency. In some instances, the central government debt ratio may be higher than the general government debt ratio, likely due to the consolidation of intra-government claims. | F56: https://www.igcp.pt/en/1-4-399/statistics/government-debt/ | G56: 2
A57: =VLOOKUP(B57,countrylist!$B$1:$C$191,2,0) -> EUR | B57: 968 | C57: Romania | D57: 1 | E57: Romania Ministry of Finance | F57: http://discutii.mfinante.ro/static/10/Mfp/buletin/executii/Structuradatorieipublice2000-2017septEng.pdf | G57: 1
A58: =VLOOKUP(B58,countrylist!$B$1:$C$191,2,0) -> EUR | B58: 936 | C58: Slovak Republic | D58: 1 | E58: National Bank of Slovakia | G58: 1
A59: =VLOOKUP(B59,countrylist!$B$1:$C$191,2,0) -> EUR | B59: 961 | C59: Slovenia | D59: 1 | E59: Republic of Slovenia Statistics Office (general government debt), and Ministry of Finance (central government debt) | F59: http://pxweb.stat.si/pxweb/Dialog/varval.asp?ma=0314905E&ti=&path=../Database/Economy/03_national_accounts/25_03149_government_accounts/&lang=1 http://www.mf.gov.si/en/investor_relations_disclaimer/the_issuer/central_government_budget_debt/ | G59: 2
A60: =VLOOKUP(B60,countrylist!$B$1:$C$191,2,0) -> EUR | B60: 184 | C60: Spain | D60: 1 | E60: Bank of Spain | F60: http://app.bde.es/bie_www/faces/bie_wwwias/jsp/op/BusquedaTematica/PBusquedaTematicaV2.jsp | G60: 1
A61: =VLOOKUP(B61,countrylist!$B$1:$C$191,2,0) -> EUR | B61: 144 | C61: Sweden | D61: 1 | E61: Statistics Sweden, and Swedish National Debt Office | F61: (private) http://www.statistikdatabasen.scb.se/pxweb/en/ssd/START__FM__FM0103__FM0103A/FirENS2010ofAr/?rxid=5432f24c-4e75-44ea-b83b-8ea147b1ce44; (public) https://www.riksgalden.se/en/aboutsndo/Central-government-debt-and-finances/Central-government-debt-an-overview/Historical-datal-diagrams/ | G61: 2
A62: =VLOOKUP(B62,countrylist!$B$1:$C$191,2,0) -> EUR | B62: 146 | C62: Switzerland | D62: 1 | E62: Federal Statistical Office Switzerland, and Swiss National Bank | F62: https://www.bfs.admin.ch/bfs/fr/home/statistiques/administration-finances-publiques.assetdetail.106548.html | G62: 2
A63: =VLOOKUP(B63,countrylist!$B$1:$C$191,2,0) -> EUR | B63: 186 | C63: Türkiye | D63: 1 | E63: Republic of Turkey Prime Ministry Undersecretariat of Treasury, and Central Bank of the Republic of Turkey | F63: https://www.treasury.gov.tr/public-finance-statistics; http://www.tcmb.gov.tr/ | G63: 2
A64: =VLOOKUP(B64,countrylist!$B$1:$C$191,2,0) -> EUR | B64: 926 | C64: Ukraine | D64: 1 | E64: National Bank of Ukraine | F64: https://bank.gov.ua/control/en/publish/article?showHidden=1&art_id=27893044&cat_id=8782106&ctime=1456402130048#1 https://bank.gov.ua/control/en/publish/article? showHidden=1&art_id=19486397&cat_id=47388#4 | G64: 1
A65: =VLOOKUP(B65,countrylist!$B$1:$C$191,2,0) -> EUR | B65: 112 | C65: United Kingdom | D65: 1 | E65: United Kingdom Debt Management Office (via CEIC), and Office for National Statistics | F65: https://www.ceicdata.com/en; https://www.ons.gov.uk/economy/nationalaccounts/uksectoraccounts/datasets/unitedkingdomeconomicaccountssectorhouseholdsandnonprofitinstitutionsservinghouseholds | G65: 2
A66: =VLOOKUP(B66,countrylist!$B$1:$C$191,2,0) -> EUR | B66: 943 | C66: Montenegro | D66: 1 | E66: Montenegro Ministry of Finance | F66: http://www.mf.gov.me/en/sections/state-debt/GDDS_table/ | G66: 1
A67: =VLOOKUP(B67,countrylist!$B$1:$C$191,2,0) -> MCD | B67: 744 | C67: Tunisia | D67: 1 | E67: Central Bank of Tunisia | G67: 1
A68: =VLOOKUP(B68,countrylist!$B$1:$C$191,2,0) -> MCD | B68: 439 | C68: Jordan | E68: Central government debt includes the publicly-guaranteed debt of public entitites | G68: 0
A69: =VLOOKUP(B69,countrylist!$B$1:$C$191,2,0) -> MCD | B69: 612 | C69: Algeria | D69: 1 | E69: Monetary Survey Data | G69: 1
A70: =VLOOKUP(B70,countrylist!$B$1:$C$191,2,0) -> WHD | B70: 316 | C70: Barbados | D70: 1 | E70: the Central Bank of Barbados. The central government debt from 1994-2016 excludes the National Insurance Schemes holdings of government paper | F70: http://data.centralbank.org.bb/TermsOfUse.aspx | G70: 1
A71: =VLOOKUP(B71,countrylist!$B$1:$C$191,2,0) -> WHD | B71: 218 | C71: Bolivia | D71: 1 | E71: Bolivia Ministry of Finance. Non-financial public sector debt include small financial sector institution | G71: 1
A72: =VLOOKUP(B72,countrylist!$B$1:$C$191,2,0) -> WHD | B72: 156 | C72: Canada | D72: 1 | E72: Department of Finance (via CEIC), and Statistics of Canada | F72: http://www65.statcan.gc.ca/acyb_r000-eng.htm | G72: 1
A73: =VLOOKUP(B73,countrylist!$B$1:$C$191,2,0) -> WHD | B73: 228 | C73: Chile | D73: 1 | E73: Ministry of Finance Chile | F73: http://www.hacienda.gob.cl/english/public-debt-office/statistics/public-debt.html | G73: 1
A74: =VLOOKUP(B74,countrylist!$B$1:$C$191,2,0) -> WHD | B74: 243 | C74: Dominican Republic | D74: 1 | E74: Ministry of Finance Dominican Republic | G74: 1
A75: =VLOOKUP(B75,countrylist!$B$1:$C$191,2,0) -> WHD | B75: 248 | C75: Ecuador | D75: 1 | E75: Ministry of Finance Ecuador | G75: 1
A76: =VLOOKUP(B76,countrylist!$B$1:$C$191,2,0) -> WHD | B76: 253 | C76: El Salvador | D76: 1 | E76: Central Bank of El Salvador | F76: http://www.bcr.gob.sv/bcrsite/?cat=1000&lang=en | G76: 1
A77: =VLOOKUP(B77,countrylist!$B$1:$C$191,2,0) -> WHD | B77: 258 | C77: Guatemala | D77: 1 | E77: Guatemala Ministry of Finance | F77: http://dcp-web.minfin.gob.gt/Documentos/Estadisticas/Reporte_Operaciones_Credito_Publico.pdf | G77: 1
A78: =VLOOKUP(B78,countrylist!$B$1:$C$191,2,0) -> WHD | B78: 268 | C78: Honduras | D78: 1 | E78: Central Bank of Honduras, and Honduras Ministry of Finance | F78: http://www.bch.hn/sector_fiscal.php | G78: 2
A79: =VLOOKUP(B79,countrylist!$B$1:$C$191,2,0) -> WHD | B79: 343 | C79: Jamaica | D79: 1 | E79: Jamaica Ministry of Finance and the Public Service | F79: http://online.mof.gov.jm/dmu/default.asp?c=1100&page=1102 | G79: 1
A80: =VLOOKUP(B80,countrylist!$B$1:$C$191,2,0) -> WHD | B80: 273 | C80: Mexico | D80: 1 | E80: Mexico Ministry of Finance. Due to data limitation, only the loans and debt securities of the household were added with the nonfinancial corporation all instruments to derive the 'all instrument' series. The central government debt only includes the federal government and the federal government state-owned enterprises. Public sector debt series exclude debt liabilities issued by state and local governments (which, according to the 2018 Fiscal Transparency Evaluation Report amounted to respectively 3.3 and 0.3% of GDP in 2016). In addition, government securities issued for central bank monetary operations are excluded from central government debt series (about 25 percent of GDP in 2016, of which 4.9 percent of GDP are marketed and the proceeds held in a restricted account in favor of the Ministry of Finance.) | F80: http://finanzaspublicas.hacienda.gob.mx/es/Finanzas_Publicas/Estadisticas_Oportunas_de_Finanzas_Publicas | G80: 1
A81: =VLOOKUP(B81,countrylist!$B$1:$C$191,2,0) -> WHD | B81: 278 | C81: Nicaragua | D81: 1 | E81: Central Bank of Nicaragua | F81: http://www.bcn.gob.ni/estadisticas/finanzas_publicas/finanzas/index.php | G81: 1
A82: =VLOOKUP(B82,countrylist!$B$1:$C$191,2,0) -> WHD | B82: 288 | C82: Paraguay | D82: 1 | E82: Treasury Paraguay. The monetary public corporations (MPC) only include the central bank. | F82: http://www.economia.gov.py/index.php/dependencias/direccion-de-politica-de-endeudamiento/presentacion-pais/deuda-publica-clasificacion-saldo-desembolso-servicio | G82: 1
A83: =VLOOKUP(B83,countrylist!$B$1:$C$191,2,0) -> WHD | B83: 293 | C83: Peru | D83: 1 | E83: Central Reserve Bank of Peru | F83: https://estadisticas.bcrp.gob.pe/estadisticas/series/anuales/resultados/PM10188FA/html https://estadisticas.bcrp.gob.pe/estadisticas/series/mensuales/resultados/PN00502MM/html https://estadisticas.bcrp.gob.pe/estadisticas/series/mensuales/resultados/PN00532MM/html https://estadisticas.bcrp.gob.pe/estadisticas/series/mensuales/resultados/PN00533MM/html https://estadisticas.bcrp.gob.pe/estadisticas/series/mensuales/resultados/PN00534MM/html | G83: 1
A84: =VLOOKUP(B84,countrylist!$B$1:$C$191,2,0) -> WHD | B84: 111 | C84: United States | D84: 1 | E84: United States Federal Reserve Bank | G84: 1
A85: =VLOOKUP(B85,countrylist!$B$1:$C$191,2,0) -> WHD | B85: 298 | C85: Uruguay | D85: 1 | E85: Central Bank of Uruguay (via CEIC) | F85: https://www.ceicdata.com/en | G85: 1
A86: =VLOOKUP(B86,countrylist!$B$1:$C$191,2,0) -> APD | B86: 532 | C86: Hong Kong SAR | D86: 1 | E86: Government Finance Statistics Yearbook | G86: 1
A87: APD | B87: 866 | C87: Tonga | D87: 0 | E87: Central Government debt data are reported for the end of the fiscal year, which runs from July to June (for example, 2018 Central Government debt is measured at the end of June 2018).
